{
  "a_comp_cor_00": {
    "CumulativeVarianceExplained": 0.0333486903,
    "Mask": "combined",
    "Method": "aCompCor",
    "Retained": true,
    "SingularValue": 96.5597927376,
    "VarianceExplained": 0.0333486903
  },
  "a_comp_cor_01": {
    "CumulativeVarianceExplained": 0.0606984944,
    "Mask": "combined",
    "Method": "aCompCor",
    "Retained": true,
    "SingularValue": 87.444811022,
    "VarianceExplained": 0.0273498041
  },
  "a_comp_cor_02": {
    "CumulativeVarianceExplained": 0.0789523417,
    "Mask": "combined",
    "Method": "aCompCor",
    "Retained": true,
    "SingularValue": 71.4387983274,
    "VarianceExplained": 0.0182538473
  },
  "a_comp_cor_03": {
    "CumulativeVarianceExplained": 0.0955527844,
    "Mask": "combined",
    "Method": "aCompCor",
    "Retained": true,
    "SingularValue": 68.1266083936,
    "VarianceExplained": 0.0166004427
  },
  "a_comp_cor_04": {
    "CumulativeVarianceExplained": 0.1112189007,
    "Mask": "combined",
    "Method": "aCompCor",
    "Retained": true,
    "SingularValue": 66.1816524846,
    "VarianceExplained": 0.0156661163
  },
  "a_comp_cor_05": {
    "CumulativeVarianceExplained": 0.1263524149,
    "Mask": "combined",
    "Method": "aCompCor",
    "Retained": true,
    "SingularValue": 65.0469336049,
    "VarianceExplained": 0.0151335142
  },
  "a_comp_cor_06": {
    "CumulativeVarianceExplained": 0.1408055441,
    "Mask": "combined",
    "Method": "aCompCor",
    "Retained": true,
    "SingularValue": 63.5679016991,
    "VarianceExplained": 0.0144531292
  },
  "a_comp_cor_07": {
    "CumulativeVarianceExplained": 0.1543315245,
    "Mask": "combined",
    "Method": "aCompCor",
    "Retained": true,
    "SingularValue": 61.4952129451,
    "VarianceExplained": 0.0135259803
  },
  "a_comp_cor_08": {
    "CumulativeVarianceExplained": 0.167395535,
    "Mask": "combined",
    "Method": "aCompCor",
    "Retained": true,
    "SingularValue": 60.435927916,
    "VarianceExplained": 0.0130640105
  },
  "a_comp_cor_09": {
    "CumulativeVarianceExplained": 0.1796194186,
    "Mask": "combined",
    "Method": "aCompCor",
    "Retained": true,
    "SingularValue": 58.4603669316,
    "VarianceExplained": 0.0122238836
  },
  "a_comp_cor_10": {
    "CumulativeVarianceExplained": 0.1917889556,
    "Mask": "combined",
    "Method": "aCompCor",
    "Retained": true,
    "SingularValue": 58.3302665831,
    "VarianceExplained": 0.012169537
  },
  "a_comp_cor_11": {
    "CumulativeVarianceExplained": 0.2034278126,
    "Mask": "combined",
    "Method": "aCompCor",
    "Retained": true,
    "SingularValue": 57.0442796287,
    "VarianceExplained": 0.011638857
  },
  "a_comp_cor_12": {
    "CumulativeVarianceExplained": 0.2147441397,
    "Mask": "combined",
    "Method": "aCompCor",
    "Retained": true,
    "SingularValue": 56.2483359956,
    "VarianceExplained": 0.0113163271
  },
  "a_comp_cor_13": {
    "CumulativeVarianceExplained": 0.2258621097,
    "Mask": "combined",
    "Method": "aCompCor",
    "Retained": true,
    "SingularValue": 55.7531851364,
    "VarianceExplained": 0.01111797
  },
  "a_comp_cor_14": {
    "CumulativeVarianceExplained": 0.2367882691,
    "Mask": "combined",
    "Method": "aCompCor",
    "Retained": true,
    "SingularValue": 55.2701570933,
    "VarianceExplained": 0.0109261594
  },
  "a_comp_cor_15": {
    "CumulativeVarianceExplained": 0.2473383622,
    "Mask": "combined",
    "Method": "aCompCor",
    "Retained": true,
    "SingularValue": 54.3106600632,
    "VarianceExplained": 0.0105500932
  },
  "a_comp_cor_16": {
    "CumulativeVarianceExplained": 0.2576573205,
    "Mask": "combined",
    "Method": "aCompCor",
    "Retained": true,
    "SingularValue": 53.7124374644,
    "VarianceExplained": 0.0103189582
  },
  "a_comp_cor_17": {
    "CumulativeVarianceExplained": 0.2678617758,
    "Mask": "combined",
    "Method": "aCompCor",
    "Retained": true,
    "SingularValue": 53.4135998292,
    "VarianceExplained": 0.0102044553
  },
  "a_comp_cor_18": {
    "CumulativeVarianceExplained": 0.277981551,
    "Mask": "combined",
    "Method": "aCompCor",
    "Retained": true,
    "SingularValue": 53.1915158695,
    "VarianceExplained": 0.0101197752
  },
  "a_comp_cor_19": {
    "CumulativeVarianceExplained": 0.2880758611,
    "Mask": "combined",
    "Method": "aCompCor",
    "Retained": true,
    "SingularValue": 53.1245488415,
    "VarianceExplained": 0.0100943101
  },
  "a_comp_cor_20": {
    "CumulativeVarianceExplained": 0.2980197327,
    "Mask": "combined",
    "Method": "aCompCor",
    "Retained": true,
    "SingularValue": 52.7271973507,
    "VarianceExplained": 0.0099438716
  },
  "a_comp_cor_21": {
    "CumulativeVarianceExplained": 0.3078477231,
    "Mask": "combined",
    "Method": "aCompCor",
    "Retained": true,
    "SingularValue": 52.41906792,
    "VarianceExplained": 0.0098279903
  },
  "a_comp_cor_22": {
    "CumulativeVarianceExplained": 0.3174928743,
    "Mask": "combined",
    "Method": "aCompCor",
    "Retained": true,
    "SingularValue": 51.92917882,
    "VarianceExplained": 0.0096451513
  },
  "a_comp_cor_23": {
    "CumulativeVarianceExplained": 0.327092993,
    "Mask": "combined",
    "Method": "aCompCor",
    "Retained": true,
    "SingularValue": 51.8078100934,
    "VarianceExplained": 0.0096001187
  },
  "a_comp_cor_24": {
    "CumulativeVarianceExplained": 0.3366130181,
    "Mask": "combined",
    "Method": "aCompCor",
    "Retained": true,
    "SingularValue": 51.5912415044,
    "VarianceExplained": 0.009520025
  },
  "a_comp_cor_25": {
    "CumulativeVarianceExplained": 0.3460234412,
    "Mask": "combined",
    "Method": "aCompCor",
    "Retained": true,
    "SingularValue": 51.2934025421,
    "VarianceExplained": 0.0094104231
  },
  "a_comp_cor_26": {
    "CumulativeVarianceExplained": 0.3553618912,
    "Mask": "combined",
    "Method": "aCompCor",
    "Retained": true,
    "SingularValue": 51.0968741651,
    "VarianceExplained": 0.00933845
  },
  "a_comp_cor_27": {
    "CumulativeVarianceExplained": 0.3644737929,
    "Mask": "combined",
    "Method": "aCompCor",
    "Retained": true,
    "SingularValue": 50.4732704543,
    "VarianceExplained": 0.0091119017
  },
  "a_comp_cor_28": {
    "CumulativeVarianceExplained": 0.3735721067,
    "Mask": "combined",
    "Method": "aCompCor",
    "Retained": true,
    "SingularValue": 50.4356228816,
    "VarianceExplained": 0.0090983138
  },
  "a_comp_cor_29": {
    "CumulativeVarianceExplained": 0.3825769616,
    "Mask": "combined",
    "Method": "aCompCor",
    "Retained": true,
    "SingularValue": 50.1759141728,
    "VarianceExplained": 0.0090048549
  },
  "a_comp_cor_30": {
    "CumulativeVarianceExplained": 0.3915244364,
    "Mask": "combined",
    "Method": "aCompCor",
    "Retained": true,
    "SingularValue": 50.0157949153,
    "VarianceExplained": 0.0089474748
  },
  "a_comp_cor_31": {
    "CumulativeVarianceExplained": 0.4004203464,
    "Mask": "combined",
    "Method": "aCompCor",
    "Retained": true,
    "SingularValue": 49.8714649519,
    "VarianceExplained": 0.0088959101
  },
  "a_comp_cor_32": {
    "CumulativeVarianceExplained": 0.4092789675,
    "Mask": "combined",
    "Method": "aCompCor",
    "Retained": true,
    "SingularValue": 49.7668320017,
    "VarianceExplained": 0.0088586211
  },
  "a_comp_cor_33": {
    "CumulativeVarianceExplained": 0.4180095321,
    "Mask": "combined",
    "Method": "aCompCor",
    "Retained": true,
    "SingularValue": 49.4058185022,
    "VarianceExplained": 0.0087305646
  },
  "a_comp_cor_34": {
    "CumulativeVarianceExplained": 0.4266809212,
    "Mask": "combined",
    "Method": "aCompCor",
    "Retained": true,
    "SingularValue": 49.2380983289,
    "VarianceExplained": 0.0086713891
  },
  "a_comp_cor_35": {
    "CumulativeVarianceExplained": 0.4352533217,
    "Mask": "combined",
    "Method": "aCompCor",
    "Retained": true,
    "SingularValue": 48.9562518102,
    "VarianceExplained": 0.0085724005
  },
  "a_comp_cor_36": {
    "CumulativeVarianceExplained": 0.4437429946,
    "Mask": "combined",
    "Method": "aCompCor",
    "Retained": true,
    "SingularValue": 48.719453964,
    "VarianceExplained": 0.0084896729
  },
  "a_comp_cor_37": {
    "CumulativeVarianceExplained": 0.4522098831,
    "Mask": "combined",
    "Method": "aCompCor",
    "Retained": true,
    "SingularValue": 48.6540339792,
    "VarianceExplained": 0.0084668885
  },
  "a_comp_cor_38": {
    "CumulativeVarianceExplained": 0.4605630021,
    "Mask": "combined",
    "Method": "aCompCor",
    "Retained": true,
    "SingularValue": 48.3260465918,
    "VarianceExplained": 0.008353119
  },
  "a_comp_cor_39": {
    "CumulativeVarianceExplained": 0.4688888767,
    "Mask": "combined",
    "Method": "aCompCor",
    "Retained": true,
    "SingularValue": 48.2471724942,
    "VarianceExplained": 0.0083258746
  },
  "a_comp_cor_40": {
    "CumulativeVarianceExplained": 0.4771160814,
    "Mask": "combined",
    "Method": "aCompCor",
    "Retained": true,
    "SingularValue": 47.9604318254,
    "VarianceExplained": 0.0082272047
  },
  "a_comp_cor_41": {
    "CumulativeVarianceExplained": 0.4852706001,
    "Mask": "combined",
    "Method": "aCompCor",
    "Retained": true,
    "SingularValue": 47.7481005395,
    "VarianceExplained": 0.0081545187
  },
  "a_comp_cor_42": {
    "CumulativeVarianceExplained": 0.4933120759,
    "Mask": "combined",
    "Method": "aCompCor",
    "Retained": true,
    "SingularValue": 47.4159889822,
    "VarianceExplained": 0.0080414758
  },
  "a_comp_cor_43": {
    "CumulativeVarianceExplained": 0.5013345885,
    "Mask": "combined",
    "Method": "aCompCor",
    "Retained": true,
    "SingularValue": 47.3600483278,
    "VarianceExplained": 0.0080225126
  },
  "a_comp_cor_44": {
    "CumulativeVarianceExplained": 0.1138742885,
    "Mask": "CSF",
    "Method": "aCompCor",
    "Retained": true,
    "SingularValue": 85.0922830417,
    "VarianceExplained": 0.1138742885
  },
  "a_comp_cor_45": {
    "CumulativeVarianceExplained": 0.2057544115,
    "Mask": "CSF",
    "Method": "aCompCor",
    "Retained": true,
    "SingularValue": 76.4342699479,
    "VarianceExplained": 0.091880123
  },
  "a_comp_cor_46": {
    "CumulativeVarianceExplained": 0.2885816969,
    "Mask": "CSF",
    "Method": "aCompCor",
    "Retained": true,
    "SingularValue": 72.5711577736,
    "VarianceExplained": 0.0828272854
  },
  "a_comp_cor_47": {
    "CumulativeVarianceExplained": 0.3373211547,
    "Mask": "CSF",
    "Method": "aCompCor",
    "Retained": true,
    "SingularValue": 55.6695466406,
    "VarianceExplained": 0.0487394578
  },
  "a_comp_cor_48": {
    "CumulativeVarianceExplained": 0.3774415881,
    "Mask": "CSF",
    "Method": "aCompCor",
    "Retained": true,
    "SingularValue": 50.5079970069,
    "VarianceExplained": 0.0401204335
  },
  "a_comp_cor_49": {
    "CumulativeVarianceExplained": 0.4119300003,
    "Mask": "CSF",
    "Method": "aCompCor",
    "Retained": true,
    "SingularValue": 46.8288979801,
    "VarianceExplained": 0.0344884121
  },
  "a_comp_cor_50": {
    "CumulativeVarianceExplained": 0.4448382625,
    "Mask": "CSF",
    "Method": "aCompCor",
    "Retained": true,
    "SingularValue": 45.7435443649,
    "VarianceExplained": 0.0329082622
  },
  "a_comp_cor_51": {
    "CumulativeVarianceExplained": 0.4730881564,
    "Mask": "CSF",
    "Method": "aCompCor",
    "Retained": true,
    "SingularValue": 42.382419784,
    "VarianceExplained": 0.0282498939
  },
  "a_comp_cor_52": {
    "CumulativeVarianceExplained": 0.4968026537,
    "Mask": "CSF",
    "Method": "aCompCor",
    "Retained": true,
    "SingularValue": 38.8315117931,
    "VarianceExplained": 0.0237144973
  },
  "a_comp_cor_53": {
    "CumulativeVarianceExplained": 0.517776051,
    "Mask": "CSF",
    "Method": "aCompCor",
    "Retained": true,
    "SingularValue": 36.5183990293,
    "VarianceExplained": 0.0209733973
  },
  "a_comp_cor_54": {
    "CumulativeVarianceExplained": 0.0325338047,
    "Mask": "WM",
    "Method": "aCompCor",
    "Retained": true,
    "SingularValue": 110.9349463487,
    "VarianceExplained": 0.0325338047
  },
  "a_comp_cor_55": {
    "CumulativeVarianceExplained": 0.0607038068,
    "Mask": "WM",
    "Method": "aCompCor",
    "Retained": true,
    "SingularValue": 103.2272574629,
    "VarianceExplained": 0.0281700021
  },
  "a_comp_cor_56": {
    "CumulativeVarianceExplained": 0.0795289481,
    "Mask": "WM",
    "Method": "aCompCor",
    "Retained": true,
    "SingularValue": 84.3859359214,
    "VarianceExplained": 0.0188251413
  },
  "a_comp_cor_57": {
    "CumulativeVarianceExplained": 0.0968863299,
    "Mask": "WM",
    "Method": "aCompCor",
    "Retained": true,
    "SingularValue": 81.0294812514,
    "VarianceExplained": 0.0173573818
  },
  "a_comp_cor_58": {
    "CumulativeVarianceExplained": 0.113943819,
    "Mask": "WM",
    "Method": "aCompCor",
    "Retained": true,
    "SingularValue": 80.3264365102,
    "VarianceExplained": 0.0170574891
  },
  "a_comp_cor_59": {
    "CumulativeVarianceExplained": 0.1294166655,
    "Mask": "WM",
    "Method": "aCompCor",
    "Retained": true,
    "SingularValue": 76.5043373639,
    "VarianceExplained": 0.0154728465
  },
  "a_comp_cor_60": {
    "CumulativeVarianceExplained": 0.1442991303,
    "Mask": "WM",
    "Method": "aCompCor",
    "Retained": true,
    "SingularValue": 75.0305936025,
    "VarianceExplained": 0.0148824648
  },
  "a_comp_cor_61": {
    "CumulativeVarianceExplained": 0.1579661872,
    "Mask": "WM",
    "Method": "aCompCor",
    "Retained": true,
    "SingularValue": 71.9015828188,
    "VarianceExplained": 0.0136670569
  },
  "a_comp_cor_62": {
    "CumulativeVarianceExplained": 0.171000695,
    "Mask": "WM",
    "Method": "aCompCor",
    "Retained": true,
    "SingularValue": 70.2179696835,
    "VarianceExplained": 0.0130345078
  },
  "a_comp_cor_63": {
    "CumulativeVarianceExplained": 0.1832557631,
    "Mask": "WM",
    "Method": "aCompCor",
    "Retained": true,
    "SingularValue": 68.0861557244,
    "VarianceExplained": 0.0122550681
  },
  "a_comp_cor_64": {
    "CumulativeVarianceExplained": 0.1952347099,
    "Mask": "WM",
    "Method": "aCompCor",
    "Retained": true,
    "SingularValue": 67.314754686,
    "VarianceExplained": 0.0119789468
  },
  "a_comp_cor_65": {
    "CumulativeVarianceExplained": 0.2064970487,
    "Mask": "WM",
    "Method": "aCompCor",
    "Retained": true,
    "SingularValue": 65.2702452126,
    "VarianceExplained": 0.0112623388
  },
  "a_comp_cor_66": {
    "CumulativeVarianceExplained": 0.2175915361,
    "Mask": "WM",
    "Method": "aCompCor",
    "Retained": true,
    "SingularValue": 64.7820325028,
    "VarianceExplained": 0.0110944874
  },
  "a_comp_cor_67": {
    "CumulativeVarianceExplained": 0.2282252238,
    "Mask": "WM",
    "Method": "aCompCor",
    "Retained": true,
    "SingularValue": 63.4224332133,
    "VarianceExplained": 0.0106336877
  },
  "a_comp_cor_68": {
    "CumulativeVarianceExplained": 0.238793585,
    "Mask": "WM",
    "Method": "aCompCor",
    "Retained": true,
    "SingularValue": 63.2273202177,
    "VarianceExplained": 0.0105683613
  },
  "a_comp_cor_69": {
    "CumulativeVarianceExplained": 0.2490713564,
    "Mask": "WM",
    "Method": "aCompCor",
    "Retained": true,
    "SingularValue": 62.3520054504,
    "VarianceExplained": 0.0102777714
  },
  "a_comp_cor_70": {
    "CumulativeVarianceExplained": 0.2590847268,
    "Mask": "WM",
    "Method": "aCompCor",
    "Retained": true,
    "SingularValue": 61.5447609548,
    "VarianceExplained": 0.0100133703
  },
  "a_comp_cor_71": {
    "CumulativeVarianceExplained": 0.2689582683,
    "Mask": "WM",
    "Method": "aCompCor",
    "Retained": true,
    "SingularValue": 61.1135381041,
    "VarianceExplained": 0.0098735415
  },
  "a_comp_cor_72": {
    "CumulativeVarianceExplained": 0.2787171838,
    "Mask": "WM",
    "Method": "aCompCor",
    "Retained": true,
    "SingularValue": 60.7577565791,
    "VarianceExplained": 0.0097589155
  },
  "a_comp_cor_73": {
    "CumulativeVarianceExplained": 0.2884370552,
    "Mask": "WM",
    "Method": "aCompCor",
    "Retained": true,
    "SingularValue": 60.6360926565,
    "VarianceExplained": 0.0097198713
  },
  "a_comp_cor_74": {
    "CumulativeVarianceExplained": 0.2980016539,
    "Mask": "WM",
    "Method": "aCompCor",
    "Retained": true,
    "SingularValue": 60.1498193385,
    "VarianceExplained": 0.0095645987
  },
  "a_comp_cor_75": {
    "CumulativeVarianceExplained": 0.3074504684,
    "Mask": "WM",
    "Method": "aCompCor",
    "Retained": true,
    "SingularValue": 59.784638961,
    "VarianceExplained": 0.0094488145
  },
  "a_comp_cor_76": {
    "CumulativeVarianceExplained": 0.3168313309,
    "Mask": "WM",
    "Method": "aCompCor",
    "Retained": true,
    "SingularValue": 59.5692779873,
    "VarianceExplained": 0.0093808626
  },
  "a_comp_cor_77": {
    "CumulativeVarianceExplained": 0.326091236,
    "Mask": "WM",
    "Method": "aCompCor",
    "Retained": true,
    "SingularValue": 59.1839867582,
    "VarianceExplained": 0.0092599051
  },
  "a_comp_cor_78": {
    "CumulativeVarianceExplained": 0.335221014,
    "Mask": "WM",
    "Method": "aCompCor",
    "Retained": true,
    "SingularValue": 58.7666666752,
    "VarianceExplained": 0.009129778
  },
  "a_comp_cor_79": {
    "CumulativeVarianceExplained": 0.3442360181,
    "Mask": "WM",
    "Method": "aCompCor",
    "Retained": true,
    "SingularValue": 58.3961093891,
    "VarianceExplained": 0.0090150041
  },
  "a_comp_cor_80": {
    "CumulativeVarianceExplained": 0.3532170261,
    "Mask": "WM",
    "Method": "aCompCor",
    "Retained": true,
    "SingularValue": 58.285897967,
    "VarianceExplained": 0.008981008
  },
  "a_comp_cor_81": {
    "CumulativeVarianceExplained": 0.3621300188,
    "Mask": "WM",
    "Method": "aCompCor",
    "Retained": true,
    "SingularValue": 58.0647720067,
    "VarianceExplained": 0.0089129927
  },
  "a_comp_cor_82": {
    "CumulativeVarianceExplained": 0.371017699,
    "Mask": "WM",
    "Method": "aCompCor",
    "Retained": true,
    "SingularValue": 57.9822628473,
    "VarianceExplained": 0.0088876802
  },
  "a_comp_cor_83": {
    "CumulativeVarianceExplained": 0.3797870281,
    "Mask": "WM",
    "Method": "aCompCor",
    "Retained": true,
    "SingularValue": 57.5949138292,
    "VarianceExplained": 0.008769329
  },
  "a_comp_cor_84": {
    "CumulativeVarianceExplained": 0.3884489406,
    "Mask": "WM",
    "Method": "aCompCor",
    "Retained": true,
    "SingularValue": 57.2410837683,
    "VarianceExplained": 0.0086619126
  },
  "a_comp_cor_85": {
    "CumulativeVarianceExplained": 0.3970388024,
    "Mask": "WM",
    "Method": "aCompCor",
    "Retained": true,
    "SingularValue": 57.0025176782,
    "VarianceExplained": 0.0085898618
  },
  "a_comp_cor_86": {
    "CumulativeVarianceExplained": 0.4055246163,
    "Mask": "WM",
    "Method": "aCompCor",
    "Retained": true,
    "SingularValue": 56.6562335432,
    "VarianceExplained": 0.0084858138
  },
  "a_comp_cor_87": {
    "CumulativeVarianceExplained": 0.4139688348,
    "Mask": "WM",
    "Method": "aCompCor",
    "Retained": true,
    "SingularValue": 56.5172056534,
    "VarianceExplained": 0.0084442185
  },
  "a_comp_cor_88": {
    "CumulativeVarianceExplained": 0.4223866254,
    "Mask": "WM",
    "Method": "aCompCor",
    "Retained": true,
    "SingularValue": 56.4286953686,
    "VarianceExplained": 0.0084177906
  },
  "a_comp_cor_89": {
    "CumulativeVarianceExplained": 0.4307788044,
    "Mask": "WM",
    "Method": "aCompCor",
    "Retained": true,
    "SingularValue": 56.3427862482,
    "VarianceExplained": 0.008392179
  },
  "a_comp_cor_90": {
    "CumulativeVarianceExplained": 0.4390245872,
    "Mask": "WM",
    "Method": "aCompCor",
    "Retained": true,
    "SingularValue": 55.8491918719,
    "VarianceExplained": 0.0082457827
  },
  "a_comp_cor_91": {
    "CumulativeVarianceExplained": 0.4472093562,
    "Mask": "WM",
    "Method": "aCompCor",
    "Retained": true,
    "SingularValue": 55.6421835315,
    "VarianceExplained": 0.008184769
  },
  "a_comp_cor_92": {
    "CumulativeVarianceExplained": 0.4553769695,
    "Mask": "WM",
    "Method": "aCompCor",
    "Retained": true,
    "SingularValue": 55.5838384659,
    "VarianceExplained": 0.0081676133
  },
  "a_comp_cor_93": {
    "CumulativeVarianceExplained": 0.4634722771,
    "Mask": "WM",
    "Method": "aCompCor",
    "Retained": true,
    "SingularValue": 55.3372569024,
    "VarianceExplained": 0.0080953076
  },
  "a_comp_cor_94": {
    "CumulativeVarianceExplained": 0.4715108578,
    "Mask": "WM",
    "Method": "aCompCor",
    "Retained": true,
    "SingularValue": 55.1430312051,
    "VarianceExplained": 0.0080385806
  },
  "a_comp_cor_95": {
    "CumulativeVarianceExplained": 0.4794978926,
    "Mask": "WM",
    "Method": "aCompCor",
    "Retained": true,
    "SingularValue": 54.9659502254,
    "VarianceExplained": 0.0079870349
  },
  "a_comp_cor_96": {
    "CumulativeVarianceExplained": 0.4873908991,
    "Mask": "WM",
    "Method": "aCompCor",
    "Retained": true,
    "SingularValue": 54.6414454969,
    "VarianceExplained": 0.0078930065
  },
  "a_comp_cor_97": {
    "CumulativeVarianceExplained": 0.4952458265,
    "Mask": "WM",
    "Method": "aCompCor",
    "Retained": true,
    "SingularValue": 54.5094796041,
    "VarianceExplained": 0.0078549273
  },
  "a_comp_cor_98": {
    "CumulativeVarianceExplained": 0.5030449143,
    "Mask": "WM",
    "Method": "aCompCor",
    "Retained": true,
    "SingularValue": 54.3153841517,
    "VarianceExplained": 0.0077990878
  },
  "dropped_0": {
    "CumulativeVarianceExplained": 0.5093239559,
    "Mask": "combined",
    "Method": "aCompCor",
    "Retained": false,
    "SingularValue": 47.2621126785,
    "VarianceExplained": 0.0079893674
  },
  "dropped_1": {
    "CumulativeVarianceExplained": 0.5172619183,
    "Mask": "combined",
    "Method": "aCompCor",
    "Retained": false,
    "SingularValue": 47.1098209705,
    "VarianceExplained": 0.0079379625
  },
  "dropped_10": {
    "CumulativeVarianceExplained": 0.5861578209,
    "Mask": "combined",
    "Method": "aCompCor",
    "Retained": false,
    "SingularValue": 45.6158493324,
    "VarianceExplained": 0.0074424798
  },
  "dropped_100": {
    "CumulativeVarianceExplained": 0.6634697672,
    "Mask": "CSF",
    "Method": "aCompCor",
    "Retained": false,
    "SingularValue": 26.0297251667,
    "VarianceExplained": 0.0106557615
  },
  "dropped_101": {
    "CumulativeVarianceExplained": 0.673520958,
    "Mask": "CSF",
    "Method": "aCompCor",
    "Retained": false,
    "SingularValue": 25.2805254915,
    "VarianceExplained": 0.0100511908
  },
  "dropped_102": {
    "CumulativeVarianceExplained": 0.6828589796,
    "Mask": "CSF",
    "Method": "aCompCor",
    "Retained": false,
    "SingularValue": 24.367152077,
    "VarianceExplained": 0.0093380216
  },
  "dropped_103": {
    "CumulativeVarianceExplained": 0.6914260442,
    "Mask": "CSF",
    "Method": "aCompCor",
    "Retained": false,
    "SingularValue": 23.3395973967,
    "VarianceExplained": 0.0085670647
  },
  "dropped_104": {
    "CumulativeVarianceExplained": 0.6994311889,
    "Mask": "CSF",
    "Method": "aCompCor",
    "Retained": false,
    "SingularValue": 22.5611862832,
    "VarianceExplained": 0.0080051447
  },
  "dropped_105": {
    "CumulativeVarianceExplained": 0.7070379203,
    "Mask": "CSF",
    "Method": "aCompCor",
    "Retained": false,
    "SingularValue": 21.992590004,
    "VarianceExplained": 0.0076067314
  },
  "dropped_106": {
    "CumulativeVarianceExplained": 0.7142998331,
    "Mask": "CSF",
    "Method": "aCompCor",
    "Retained": false,
    "SingularValue": 21.4883391947,
    "VarianceExplained": 0.0072619127
  },
  "dropped_107": {
    "CumulativeVarianceExplained": 0.7213404368,
    "Mask": "CSF",
    "Method": "aCompCor",
    "Retained": false,
    "SingularValue": 21.1583739635,
    "VarianceExplained": 0.0070406037
  },
  "dropped_108": {
    "CumulativeVarianceExplained": 0.7282396961,
    "Mask": "CSF",
    "Method": "aCompCor",
    "Retained": false,
    "SingularValue": 20.9449134709,
    "VarianceExplained": 0.0068992593
  },
  "dropped_109": {
    "CumulativeVarianceExplained": 0.7350897767,
    "Mask": "CSF",
    "Method": "aCompCor",
    "Retained": false,
    "SingularValue": 20.8701312836,
    "VarianceExplained": 0.0068500807
  },
  "dropped_11": {
    "CumulativeVarianceExplained": 0.5934974669,
    "Mask": "combined",
    "Method": "aCompCor",
    "Retained": false,
    "SingularValue": 45.2996125981,
    "VarianceExplained": 0.0073396459
  },
  "dropped_110": {
    "CumulativeVarianceExplained": 0.7417825092,
    "Mask": "CSF",
    "Method": "aCompCor",
    "Retained": false,
    "SingularValue": 20.6290424472,
    "VarianceExplained": 0.0066927324
  },
  "dropped_111": {
    "CumulativeVarianceExplained": 0.7482369656,
    "Mask": "CSF",
    "Method": "aCompCor",
    "Retained": false,
    "SingularValue": 20.2584947585,
    "VarianceExplained": 0.0064544564
  },
  "dropped_112": {
    "CumulativeVarianceExplained": 0.7543568727,
    "Mask": "CSF",
    "Method": "aCompCor",
    "Retained": false,
    "SingularValue": 19.7264871826,
    "VarianceExplained": 0.0061199072
  },
  "dropped_113": {
    "CumulativeVarianceExplained": 0.7603482884,
    "Mask": "CSF",
    "Method": "aCompCor",
    "Retained": false,
    "SingularValue": 19.5183033869,
    "VarianceExplained": 0.0059914157
  },
  "dropped_114": {
    "CumulativeVarianceExplained": 0.7662919646,
    "Mask": "CSF",
    "Method": "aCompCor",
    "Retained": false,
    "SingularValue": 19.4403870971,
    "VarianceExplained": 0.0059436762
  },
  "dropped_115": {
    "CumulativeVarianceExplained": 0.772046406,
    "Mask": "CSF",
    "Method": "aCompCor",
    "Retained": false,
    "SingularValue": 19.1284122347,
    "VarianceExplained": 0.0057544414
  },
  "dropped_116": {
    "CumulativeVarianceExplained": 0.7776540307,
    "Mask": "CSF",
    "Method": "aCompCor",
    "Retained": false,
    "SingularValue": 18.8828179895,
    "VarianceExplained": 0.0056076247
  },
  "dropped_117": {
    "CumulativeVarianceExplained": 0.7832308327,
    "Mask": "CSF",
    "Method": "aCompCor",
    "Retained": false,
    "SingularValue": 18.8308512078,
    "VarianceExplained": 0.005576802
  },
  "dropped_118": {
    "CumulativeVarianceExplained": 0.7887121738,
    "Mask": "CSF",
    "Method": "aCompCor",
    "Retained": false,
    "SingularValue": 18.6689869,
    "VarianceExplained": 0.0054813411
  },
  "dropped_119": {
    "CumulativeVarianceExplained": 0.7940349842,
    "Mask": "CSF",
    "Method": "aCompCor",
    "Retained": false,
    "SingularValue": 18.3970351844,
    "VarianceExplained": 0.0053228105
  },
  "dropped_12": {
    "CumulativeVarianceExplained": 0.600735432,
    "Mask": "combined",
    "Method": "aCompCor",
    "Retained": false,
    "SingularValue": 44.9847360235,
    "VarianceExplained": 0.0072379651
  },
  "dropped_120": {
    "CumulativeVarianceExplained": 0.7991551662,
    "Mask": "CSF",
    "Method": "aCompCor",
    "Retained": false,
    "SingularValue": 18.0434689113,
    "VarianceExplained": 0.005120182
  },
  "dropped_121": {
    "CumulativeVarianceExplained": 0.8041446909,
    "Mask": "CSF",
    "Method": "aCompCor",
    "Retained": false,
    "SingularValue": 17.811763671,
    "VarianceExplained": 0.0049895247
  },
  "dropped_122": {
    "CumulativeVarianceExplained": 0.8090859316,
    "Mask": "CSF",
    "Method": "aCompCor",
    "Retained": false,
    "SingularValue": 17.725371485,
    "VarianceExplained": 0.0049412408
  },
  "dropped_123": {
    "CumulativeVarianceExplained": 0.8137961299,
    "Mask": "CSF",
    "Method": "aCompCor",
    "Retained": false,
    "SingularValue": 17.3060093592,
    "VarianceExplained": 0.0047101983
  },
  "dropped_124": {
    "CumulativeVarianceExplained": 0.8184090875,
    "Mask": "CSF",
    "Method": "aCompCor",
    "Retained": false,
    "SingularValue": 17.1264387701,
    "VarianceExplained": 0.0046129575
  },
  "dropped_125": {
    "CumulativeVarianceExplained": 0.8229852531,
    "Mask": "CSF",
    "Method": "aCompCor",
    "Retained": false,
    "SingularValue": 17.0580037479,
    "VarianceExplained": 0.0045761656
  },
  "dropped_126": {
    "CumulativeVarianceExplained": 0.8274010021,
    "Mask": "CSF",
    "Method": "aCompCor",
    "Retained": false,
    "SingularValue": 16.756354061,
    "VarianceExplained": 0.004415749
  },
  "dropped_127": {
    "CumulativeVarianceExplained": 0.8317632501,
    "Mask": "CSF",
    "Method": "aCompCor",
    "Retained": false,
    "SingularValue": 16.6545351084,
    "VarianceExplained": 0.004362248
  },
  "dropped_128": {
    "CumulativeVarianceExplained": 0.8360042979,
    "Mask": "CSF",
    "Method": "aCompCor",
    "Retained": false,
    "SingularValue": 16.4215414219,
    "VarianceExplained": 0.0042410478
  },
  "dropped_129": {
    "CumulativeVarianceExplained": 0.8401331711,
    "Mask": "CSF",
    "Method": "aCompCor",
    "Retained": false,
    "SingularValue": 16.2029133095,
    "VarianceExplained": 0.0041288732
  },
  "dropped_13": {
    "CumulativeVarianceExplained": 0.6079627994,
    "Mask": "combined",
    "Method": "aCompCor",
    "Retained": false,
    "SingularValue": 44.9517910893,
    "VarianceExplained": 0.0072273674
  },
  "dropped_130": {
    "CumulativeVarianceExplained": 0.8441683956,
    "Mask": "CSF",
    "Method": "aCompCor",
    "Retained": false,
    "SingularValue": 16.0181070045,
    "VarianceExplained": 0.0040352245
  },
  "dropped_131": {
    "CumulativeVarianceExplained": 0.8480728325,
    "Mask": "CSF",
    "Method": "aCompCor",
    "Retained": false,
    "SingularValue": 15.7563835241,
    "VarianceExplained": 0.0039044369
  },
  "dropped_132": {
    "CumulativeVarianceExplained": 0.8518746218,
    "Mask": "CSF",
    "Method": "aCompCor",
    "Retained": false,
    "SingularValue": 15.547886386,
    "VarianceExplained": 0.0038017893
  },
  "dropped_133": {
    "CumulativeVarianceExplained": 0.8555594897,
    "Mask": "CSF",
    "Method": "aCompCor",
    "Retained": false,
    "SingularValue": 15.306937233,
    "VarianceExplained": 0.0036848679
  },
  "dropped_134": {
    "CumulativeVarianceExplained": 0.8591771809,
    "Mask": "CSF",
    "Method": "aCompCor",
    "Retained": false,
    "SingularValue": 15.1667692758,
    "VarianceExplained": 0.0036176911
  },
  "dropped_135": {
    "CumulativeVarianceExplained": 0.8627785259,
    "Mask": "CSF",
    "Method": "aCompCor",
    "Retained": false,
    "SingularValue": 15.132465942,
    "VarianceExplained": 0.0036013451
  },
  "dropped_136": {
    "CumulativeVarianceExplained": 0.8663155525,
    "Mask": "CSF",
    "Method": "aCompCor",
    "Retained": false,
    "SingularValue": 14.9967274942,
    "VarianceExplained": 0.0035370266
  },
  "dropped_137": {
    "CumulativeVarianceExplained": 0.8697701693,
    "Mask": "CSF",
    "Method": "aCompCor",
    "Retained": false,
    "SingularValue": 14.8209921364,
    "VarianceExplained": 0.0034546168
  },
  "dropped_138": {
    "CumulativeVarianceExplained": 0.8731219127,
    "Mask": "CSF",
    "Method": "aCompCor",
    "Retained": false,
    "SingularValue": 14.5986507546,
    "VarianceExplained": 0.0033517434
  },
  "dropped_139": {
    "CumulativeVarianceExplained": 0.8764686957,
    "Mask": "CSF",
    "Method": "aCompCor",
    "Retained": false,
    "SingularValue": 14.5878442241,
    "VarianceExplained": 0.003346783
  },
  "dropped_14": {
    "CumulativeVarianceExplained": 0.6151303625,
    "Mask": "combined",
    "Method": "aCompCor",
    "Retained": false,
    "SingularValue": 44.7654234841,
    "VarianceExplained": 0.0071675631
  },
  "dropped_140": {
    "CumulativeVarianceExplained": 0.8796663207,
    "Mask": "CSF",
    "Method": "aCompCor",
    "Retained": false,
    "SingularValue": 14.2590667865,
    "VarianceExplained": 0.003197625
  },
  "dropped_141": {
    "CumulativeVarianceExplained": 0.8828252533,
    "Mask": "CSF",
    "Method": "aCompCor",
    "Retained": false,
    "SingularValue": 14.1725341839,
    "VarianceExplained": 0.0031589325
  },
  "dropped_142": {
    "CumulativeVarianceExplained": 0.8859199981,
    "Mask": "CSF",
    "Method": "aCompCor",
    "Retained": false,
    "SingularValue": 14.0278064196,
    "VarianceExplained": 0.0030947449
  },
  "dropped_143": {
    "CumulativeVarianceExplained": 0.8889879054,
    "Mask": "CSF",
    "Method": "aCompCor",
    "Retained": false,
    "SingularValue": 13.966849434,
    "VarianceExplained": 0.0030679073
  },
  "dropped_144": {
    "CumulativeVarianceExplained": 0.8920254282,
    "Mask": "CSF",
    "Method": "aCompCor",
    "Retained": false,
    "SingularValue": 13.8975136248,
    "VarianceExplained": 0.0030375228
  },
  "dropped_145": {
    "CumulativeVarianceExplained": 0.8949922166,
    "Mask": "CSF",
    "Method": "aCompCor",
    "Retained": false,
    "SingularValue": 13.7347457507,
    "VarianceExplained": 0.0029667884
  },
  "dropped_146": {
    "CumulativeVarianceExplained": 0.8978285399,
    "Mask": "CSF",
    "Method": "aCompCor",
    "Retained": false,
    "SingularValue": 13.4293566512,
    "VarianceExplained": 0.0028363233
  },
  "dropped_147": {
    "CumulativeVarianceExplained": 0.9006564694,
    "Mask": "CSF",
    "Method": "aCompCor",
    "Retained": false,
    "SingularValue": 13.4094703138,
    "VarianceExplained": 0.0028279295
  },
  "dropped_148": {
    "CumulativeVarianceExplained": 0.9034226836,
    "Mask": "CSF",
    "Method": "aCompCor",
    "Retained": false,
    "SingularValue": 13.2623426306,
    "VarianceExplained": 0.0027662142
  },
  "dropped_149": {
    "CumulativeVarianceExplained": 0.9061623117,
    "Mask": "CSF",
    "Method": "aCompCor",
    "Retained": false,
    "SingularValue": 13.1984565626,
    "VarianceExplained": 0.0027396281
  },
  "dropped_15": {
    "CumulativeVarianceExplained": 0.6222421193,
    "Mask": "combined",
    "Method": "aCompCor",
    "Retained": false,
    "SingularValue": 44.5908120866,
    "VarianceExplained": 0.0071117568
  },
  "dropped_150": {
    "CumulativeVarianceExplained": 0.9088914675,
    "Mask": "CSF",
    "Method": "aCompCor",
    "Retained": false,
    "SingularValue": 13.1732064802,
    "VarianceExplained": 0.0027291558
  },
  "dropped_151": {
    "CumulativeVarianceExplained": 0.9115363627,
    "Mask": "CSF",
    "Method": "aCompCor",
    "Retained": false,
    "SingularValue": 12.968255802,
    "VarianceExplained": 0.0026448952
  },
  "dropped_152": {
    "CumulativeVarianceExplained": 0.9141314595,
    "Mask": "CSF",
    "Method": "aCompCor",
    "Retained": false,
    "SingularValue": 12.8455919852,
    "VarianceExplained": 0.0025950969
  },
  "dropped_153": {
    "CumulativeVarianceExplained": 0.9166903675,
    "Mask": "CSF",
    "Method": "aCompCor",
    "Retained": false,
    "SingularValue": 12.7557110315,
    "VarianceExplained": 0.002558908
  },
  "dropped_154": {
    "CumulativeVarianceExplained": 0.9191330139,
    "Mask": "CSF",
    "Method": "aCompCor",
    "Retained": false,
    "SingularValue": 12.4625707792,
    "VarianceExplained": 0.0024426464
  },
  "dropped_155": {
    "CumulativeVarianceExplained": 0.9215490874,
    "Mask": "CSF",
    "Method": "aCompCor",
    "Retained": false,
    "SingularValue": 12.3945971191,
    "VarianceExplained": 0.0024160736
  },
  "dropped_156": {
    "CumulativeVarianceExplained": 0.9239133715,
    "Mask": "CSF",
    "Method": "aCompCor",
    "Retained": false,
    "SingularValue": 12.2610359078,
    "VarianceExplained": 0.0023642841
  },
  "dropped_157": {
    "CumulativeVarianceExplained": 0.9262598104,
    "Mask": "CSF",
    "Method": "aCompCor",
    "Retained": false,
    "SingularValue": 12.2146763073,
    "VarianceExplained": 0.0023464389
  },
  "dropped_158": {
    "CumulativeVarianceExplained": 0.9285651853,
    "Mask": "CSF",
    "Method": "aCompCor",
    "Retained": false,
    "SingularValue": 12.1073227177,
    "VarianceExplained": 0.0023053749
  },
  "dropped_159": {
    "CumulativeVarianceExplained": 0.9308560938,
    "Mask": "CSF",
    "Method": "aCompCor",
    "Retained": false,
    "SingularValue": 12.0692756947,
    "VarianceExplained": 0.0022909085
  },
  "dropped_16": {
    "CumulativeVarianceExplained": 0.6293332401,
    "Mask": "combined",
    "Method": "aCompCor",
    "Retained": false,
    "SingularValue": 44.5260711107,
    "VarianceExplained": 0.0070911208
  },
  "dropped_160": {
    "CumulativeVarianceExplained": 0.9331091996,
    "Mask": "CSF",
    "Method": "aCompCor",
    "Retained": false,
    "SingularValue": 11.9692830273,
    "VarianceExplained": 0.0022531059
  },
  "dropped_161": {
    "CumulativeVarianceExplained": 0.9353083455,
    "Mask": "CSF",
    "Method": "aCompCor",
    "Retained": false,
    "SingularValue": 11.8250874148,
    "VarianceExplained": 0.0021991459
  },
  "dropped_162": {
    "CumulativeVarianceExplained": 0.9374742762,
    "Mask": "CSF",
    "Method": "aCompCor",
    "Retained": false,
    "SingularValue": 11.7354463647,
    "VarianceExplained": 0.0021659307
  },
  "dropped_163": {
    "CumulativeVarianceExplained": 0.9395636517,
    "Mask": "CSF",
    "Method": "aCompCor",
    "Retained": false,
    "SingularValue": 11.5261850156,
    "VarianceExplained": 0.0020893755
  },
  "dropped_164": {
    "CumulativeVarianceExplained": 0.9416044635,
    "Mask": "CSF",
    "Method": "aCompCor",
    "Retained": false,
    "SingularValue": 11.3914448463,
    "VarianceExplained": 0.0020408118
  },
  "dropped_165": {
    "CumulativeVarianceExplained": 0.9435427926,
    "Mask": "CSF",
    "Method": "aCompCor",
    "Retained": false,
    "SingularValue": 11.1017412656,
    "VarianceExplained": 0.0019383292
  },
  "dropped_166": {
    "CumulativeVarianceExplained": 0.9454517007,
    "Mask": "CSF",
    "Method": "aCompCor",
    "Retained": false,
    "SingularValue": 11.0171648832,
    "VarianceExplained": 0.0019089081
  },
  "dropped_167": {
    "CumulativeVarianceExplained": 0.9473319225,
    "Mask": "CSF",
    "Method": "aCompCor",
    "Retained": false,
    "SingularValue": 10.9340705583,
    "VarianceExplained": 0.0018802217
  },
  "dropped_168": {
    "CumulativeVarianceExplained": 0.9492032048,
    "Mask": "CSF",
    "Method": "aCompCor",
    "Retained": false,
    "SingularValue": 10.9080469783,
    "VarianceExplained": 0.0018712824
  },
  "dropped_169": {
    "CumulativeVarianceExplained": 0.951022622,
    "Mask": "CSF",
    "Method": "aCompCor",
    "Retained": false,
    "SingularValue": 10.7558189502,
    "VarianceExplained": 0.0018194172
  },
  "dropped_17": {
    "CumulativeVarianceExplained": 0.636295425,
    "Mask": "combined",
    "Method": "aCompCor",
    "Retained": false,
    "SingularValue": 44.1194114627,
    "VarianceExplained": 0.0069621849
  },
  "dropped_170": {
    "CumulativeVarianceExplained": 0.9528345996,
    "Mask": "CSF",
    "Method": "aCompCor",
    "Retained": false,
    "SingularValue": 10.7338061853,
    "VarianceExplained": 0.0018119776
  },
  "dropped_171": {
    "CumulativeVarianceExplained": 0.9546090704,
    "Mask": "CSF",
    "Method": "aCompCor",
    "Retained": false,
    "SingularValue": 10.6221336585,
    "VarianceExplained": 0.0017744708
  },
  "dropped_172": {
    "CumulativeVarianceExplained": 0.9563262969,
    "Mask": "CSF",
    "Method": "aCompCor",
    "Retained": false,
    "SingularValue": 10.4493945942,
    "VarianceExplained": 0.0017172265
  },
  "dropped_173": {
    "CumulativeVarianceExplained": 0.9580167256,
    "Mask": "CSF",
    "Method": "aCompCor",
    "Retained": false,
    "SingularValue": 10.3675411375,
    "VarianceExplained": 0.0016904287
  },
  "dropped_174": {
    "CumulativeVarianceExplained": 0.9596873661,
    "Mask": "CSF",
    "Method": "aCompCor",
    "Retained": false,
    "SingularValue": 10.3066813373,
    "VarianceExplained": 0.0016706406
  },
  "dropped_175": {
    "CumulativeVarianceExplained": 0.9613163094,
    "Mask": "CSF",
    "Method": "aCompCor",
    "Retained": false,
    "SingularValue": 10.1772469208,
    "VarianceExplained": 0.0016289432
  },
  "dropped_176": {
    "CumulativeVarianceExplained": 0.9628951043,
    "Mask": "CSF",
    "Method": "aCompCor",
    "Retained": false,
    "SingularValue": 10.0193652257,
    "VarianceExplained": 0.001578795
  },
  "dropped_177": {
    "CumulativeVarianceExplained": 0.964437826,
    "Mask": "CSF",
    "Method": "aCompCor",
    "Retained": false,
    "SingularValue": 9.904239318,
    "VarianceExplained": 0.0015427217
  },
  "dropped_178": {
    "CumulativeVarianceExplained": 0.9659568431,
    "Mask": "CSF",
    "Method": "aCompCor",
    "Retained": false,
    "SingularValue": 9.827853358,
    "VarianceExplained": 0.0015190171
  },
  "dropped_179": {
    "CumulativeVarianceExplained": 0.9674210692,
    "Mask": "CSF",
    "Method": "aCompCor",
    "Retained": false,
    "SingularValue": 9.6489802727,
    "VarianceExplained": 0.0014642262
  },
  "dropped_18": {
    "CumulativeVarianceExplained": 0.6432329791,
    "Mask": "combined",
    "Method": "aCompCor",
    "Retained": false,
    "SingularValue": 44.0412993437,
    "VarianceExplained": 0.006937554
  },
  "dropped_180": {
    "CumulativeVarianceExplained": 0.9688731621,
    "Mask": "CSF",
    "Method": "aCompCor",
    "Retained": false,
    "SingularValue": 9.6089188513,
    "VarianceExplained": 0.0014520928
  },
  "dropped_181": {
    "CumulativeVarianceExplained": 0.9702733971,
    "Mask": "CSF",
    "Method": "aCompCor",
    "Retained": false,
    "SingularValue": 9.4357800964,
    "VarianceExplained": 0.0014002351
  },
  "dropped_182": {
    "CumulativeVarianceExplained": 0.9716605561,
    "Mask": "CSF",
    "Method": "aCompCor",
    "Retained": false,
    "SingularValue": 9.3916187307,
    "VarianceExplained": 0.001387159
  },
  "dropped_183": {
    "CumulativeVarianceExplained": 0.9730378679,
    "Mask": "CSF",
    "Method": "aCompCor",
    "Retained": false,
    "SingularValue": 9.3582247587,
    "VarianceExplained": 0.0013773118
  },
  "dropped_184": {
    "CumulativeVarianceExplained": 0.9744014643,
    "Mask": "CSF",
    "Method": "aCompCor",
    "Retained": false,
    "SingularValue": 9.3115133131,
    "VarianceExplained": 0.0013635964
  },
  "dropped_185": {
    "CumulativeVarianceExplained": 0.9757402629,
    "Mask": "CSF",
    "Method": "aCompCor",
    "Retained": false,
    "SingularValue": 9.226456817,
    "VarianceExplained": 0.0013387985
  },
  "dropped_186": {
    "CumulativeVarianceExplained": 0.9770296361,
    "Mask": "CSF",
    "Method": "aCompCor",
    "Retained": false,
    "SingularValue": 9.0545456516,
    "VarianceExplained": 0.0012893732
  },
  "dropped_187": {
    "CumulativeVarianceExplained": 0.9783075112,
    "Mask": "CSF",
    "Method": "aCompCor",
    "Retained": false,
    "SingularValue": 9.0140826386,
    "VarianceExplained": 0.0012778751
  },
  "dropped_188": {
    "CumulativeVarianceExplained": 0.9795516453,
    "Mask": "CSF",
    "Method": "aCompCor",
    "Retained": false,
    "SingularValue": 8.8942829066,
    "VarianceExplained": 0.0012441341
  },
  "dropped_189": {
    "CumulativeVarianceExplained": 0.9807588254,
    "Mask": "CSF",
    "Method": "aCompCor",
    "Retained": false,
    "SingularValue": 8.761195732,
    "VarianceExplained": 0.0012071802
  },
  "dropped_19": {
    "CumulativeVarianceExplained": 0.6501479403,
    "Mask": "combined",
    "Method": "aCompCor",
    "Retained": false,
    "SingularValue": 43.9695284163,
    "VarianceExplained": 0.0069149612
  },
  "dropped_190": {
    "CumulativeVarianceExplained": 0.981941903,
    "Mask": "CSF",
    "Method": "aCompCor",
    "Retained": false,
    "SingularValue": 8.6732915281,
    "VarianceExplained": 0.0011830775
  },
  "dropped_191": {
    "CumulativeVarianceExplained": 0.9830667286,
    "Mask": "CSF",
    "Method": "aCompCor",
    "Retained": false,
    "SingularValue": 8.457070066,
    "VarianceExplained": 0.0011248256
  },
  "dropped_192": {
    "CumulativeVarianceExplained": 0.9841787343,
    "Mask": "CSF",
    "Method": "aCompCor",
    "Retained": false,
    "SingularValue": 8.4087383814,
    "VarianceExplained": 0.0011120057
  },
  "dropped_193": {
    "CumulativeVarianceExplained": 0.9852574704,
    "Mask": "CSF",
    "Method": "aCompCor",
    "Retained": false,
    "SingularValue": 8.2819947426,
    "VarianceExplained": 0.0010787361
  },
  "dropped_194": {
    "CumulativeVarianceExplained": 0.9863096279,
    "Mask": "CSF",
    "Method": "aCompCor",
    "Retained": false,
    "SingularValue": 8.1793296177,
    "VarianceExplained": 0.0010521575
  },
  "dropped_195": {
    "CumulativeVarianceExplained": 0.987310976,
    "Mask": "CSF",
    "Method": "aCompCor",
    "Retained": false,
    "SingularValue": 7.9793934211,
    "VarianceExplained": 0.0010013481
  },
  "dropped_196": {
    "CumulativeVarianceExplained": 0.988305132,
    "Mask": "CSF",
    "Method": "aCompCor",
    "Retained": false,
    "SingularValue": 7.9506864016,
    "VarianceExplained": 0.0009941561
  },
  "dropped_197": {
    "CumulativeVarianceExplained": 0.9892738851,
    "Mask": "CSF",
    "Method": "aCompCor",
    "Retained": false,
    "SingularValue": 7.8484498947,
    "VarianceExplained": 0.0009687531
  },
  "dropped_198": {
    "CumulativeVarianceExplained": 0.9902078897,
    "Mask": "CSF",
    "Method": "aCompCor",
    "Retained": false,
    "SingularValue": 7.7064050732,
    "VarianceExplained": 0.0009340045
  },
  "dropped_199": {
    "CumulativeVarianceExplained": 0.9911052249,
    "Mask": "CSF",
    "Method": "aCompCor",
    "Retained": false,
    "SingularValue": 7.5536124277,
    "VarianceExplained": 0.0008973352
  },
  "dropped_2": {
    "CumulativeVarianceExplained": 0.5251523851,
    "Mask": "combined",
    "Method": "aCompCor",
    "Retained": false,
    "SingularValue": 46.9686718766,
    "VarianceExplained": 0.0078904667
  },
  "dropped_20": {
    "CumulativeVarianceExplained": 0.656997337,
    "Mask": "combined",
    "Method": "aCompCor",
    "Retained": false,
    "SingularValue": 43.7605824132,
    "VarianceExplained": 0.0068493967
  },
  "dropped_200": {
    "CumulativeVarianceExplained": 0.9919808533,
    "Mask": "CSF",
    "Method": "aCompCor",
    "Retained": false,
    "SingularValue": 7.4616908711,
    "VarianceExplained": 0.0008756284
  },
  "dropped_201": {
    "CumulativeVarianceExplained": 0.9928336963,
    "Mask": "CSF",
    "Method": "aCompCor",
    "Retained": false,
    "SingularValue": 7.3639679842,
    "VarianceExplained": 0.000852843
  },
  "dropped_202": {
    "CumulativeVarianceExplained": 0.9936759137,
    "Mask": "CSF",
    "Method": "aCompCor",
    "Retained": false,
    "SingularValue": 7.3179499719,
    "VarianceExplained": 0.0008422174
  },
  "dropped_203": {
    "CumulativeVarianceExplained": 0.9945089859,
    "Mask": "CSF",
    "Method": "aCompCor",
    "Retained": false,
    "SingularValue": 7.2781108486,
    "VarianceExplained": 0.0008330722
  },
  "dropped_204": {
    "CumulativeVarianceExplained": 0.9952936465,
    "Mask": "CSF",
    "Method": "aCompCor",
    "Retained": false,
    "SingularValue": 7.0634725146,
    "VarianceExplained": 0.0007846606
  },
  "dropped_205": {
    "CumulativeVarianceExplained": 0.9960553581,
    "Mask": "CSF",
    "Method": "aCompCor",
    "Retained": false,
    "SingularValue": 6.9594129967,
    "VarianceExplained": 0.0007617116
  },
  "dropped_206": {
    "CumulativeVarianceExplained": 0.9967951713,
    "Mask": "CSF",
    "Method": "aCompCor",
    "Retained": false,
    "SingularValue": 6.8586457052,
    "VarianceExplained": 0.0007398132
  },
  "dropped_207": {
    "CumulativeVarianceExplained": 0.9975030053,
    "Mask": "CSF",
    "Method": "aCompCor",
    "Retained": false,
    "SingularValue": 6.7087722978,
    "VarianceExplained": 0.000707834
  },
  "dropped_208": {
    "CumulativeVarianceExplained": 0.9981658119,
    "Mask": "CSF",
    "Method": "aCompCor",
    "Retained": false,
    "SingularValue": 6.4918839718,
    "VarianceExplained": 0.0006628066
  },
  "dropped_209": {
    "CumulativeVarianceExplained": 0.9988103656,
    "Mask": "CSF",
    "Method": "aCompCor",
    "Retained": false,
    "SingularValue": 6.4018706982,
    "VarianceExplained": 0.0006445537
  },
  "dropped_21": {
    "CumulativeVarianceExplained": 0.6638247532,
    "Mask": "combined",
    "Method": "aCompCor",
    "Retained": false,
    "SingularValue": 43.6903096732,
    "VarianceExplained": 0.0068274162
  },
  "dropped_210": {
    "CumulativeVarianceExplained": 0.9994419909,
    "Mask": "CSF",
    "Method": "aCompCor",
    "Retained": false,
    "SingularValue": 6.3373413149,
    "VarianceExplained": 0.0006316253
  },
  "dropped_211": {
    "CumulativeVarianceExplained": 1.0,
    "Mask": "CSF",
    "Method": "aCompCor",
    "Retained": false,
    "SingularValue": 5.9565936828,
    "VarianceExplained": 0.0005580091
  },
  "dropped_212": {
    "CumulativeVarianceExplained": 1.0,
    "Mask": "CSF",
    "Method": "aCompCor",
    "Retained": false,
    "SingularValue": 0.0,
    "VarianceExplained": 0.0
  },
  "dropped_213": {
    "CumulativeVarianceExplained": 1.0,
    "Mask": "CSF",
    "Method": "aCompCor",
    "Retained": false,
    "SingularValue": 0.0,
    "VarianceExplained": 0.0
  },
  "dropped_214": {
    "CumulativeVarianceExplained": 1.0,
    "Mask": "CSF",
    "Method": "aCompCor",
    "Retained": false,
    "SingularValue": 0.0,
    "VarianceExplained": 0.0
  },
  "dropped_215": {
    "CumulativeVarianceExplained": 1.0,
    "Mask": "CSF",
    "Method": "aCompCor",
    "Retained": false,
    "SingularValue": 0.0,
    "VarianceExplained": 0.0
  },
  "dropped_216": {
    "CumulativeVarianceExplained": 0.5108071577,
    "Mask": "WM",
    "Method": "aCompCor",
    "Retained": false,
    "SingularValue": 54.1869340867,
    "VarianceExplained": 0.0077622434
  },
  "dropped_217": {
    "CumulativeVarianceExplained": 0.5185310889,
    "Mask": "WM",
    "Method": "aCompCor",
    "Retained": false,
    "SingularValue": 54.0530428395,
    "VarianceExplained": 0.0077239312
  },
  "dropped_218": {
    "CumulativeVarianceExplained": 0.5261651539,
    "Mask": "WM",
    "Method": "aCompCor",
    "Retained": false,
    "SingularValue": 53.7376753296,
    "VarianceExplained": 0.007634065
  },
  "dropped_219": {
    "CumulativeVarianceExplained": 0.5337713802,
    "Mask": "WM",
    "Method": "aCompCor",
    "Retained": false,
    "SingularValue": 53.6396052486,
    "VarianceExplained": 0.0076062264
  },
  "dropped_22": {
    "CumulativeVarianceExplained": 0.670579655,
    "Mask": "combined",
    "Method": "aCompCor",
    "Retained": false,
    "SingularValue": 43.457671652,
    "VarianceExplained": 0.0067549018
  },
  "dropped_220": {
    "CumulativeVarianceExplained": 0.5413402623,
    "Mask": "WM",
    "Method": "aCompCor",
    "Retained": false,
    "SingularValue": 53.507765891,
    "VarianceExplained": 0.007568882
  },
  "dropped_221": {
    "CumulativeVarianceExplained": 0.5487980181,
    "Mask": "WM",
    "Method": "aCompCor",
    "Retained": false,
    "SingularValue": 53.1135134424,
    "VarianceExplained": 0.0074577559
  },
  "dropped_222": {
    "CumulativeVarianceExplained": 0.5562239953,
    "Mask": "WM",
    "Method": "aCompCor",
    "Retained": false,
    "SingularValue": 53.0002298818,
    "VarianceExplained": 0.0074259771
  },
  "dropped_223": {
    "CumulativeVarianceExplained": 0.563571252,
    "Mask": "WM",
    "Method": "aCompCor",
    "Retained": false,
    "SingularValue": 52.7185621996,
    "VarianceExplained": 0.0073472567
  },
  "dropped_224": {
    "CumulativeVarianceExplained": 0.5708961265,
    "Mask": "WM",
    "Method": "aCompCor",
    "Retained": false,
    "SingularValue": 52.6382017079,
    "VarianceExplained": 0.0073248745
  },
  "dropped_225": {
    "CumulativeVarianceExplained": 0.5781388586,
    "Mask": "WM",
    "Method": "aCompCor",
    "Retained": false,
    "SingularValue": 52.3422225828,
    "VarianceExplained": 0.0072427321
  },
  "dropped_226": {
    "CumulativeVarianceExplained": 0.5853592698,
    "Mask": "WM",
    "Method": "aCompCor",
    "Retained": false,
    "SingularValue": 52.2615052857,
    "VarianceExplained": 0.0072204112
  },
  "dropped_227": {
    "CumulativeVarianceExplained": 0.5925322854,
    "Mask": "WM",
    "Method": "aCompCor",
    "Retained": false,
    "SingularValue": 52.0896980583,
    "VarianceExplained": 0.0071730157
  },
  "dropped_228": {
    "CumulativeVarianceExplained": 0.5996861826,
    "Mask": "WM",
    "Method": "aCompCor",
    "Retained": false,
    "SingularValue": 52.020233463,
    "VarianceExplained": 0.0071538972
  },
  "dropped_229": {
    "CumulativeVarianceExplained": 0.6068062254,
    "Mask": "WM",
    "Method": "aCompCor",
    "Retained": false,
    "SingularValue": 51.8969996211,
    "VarianceExplained": 0.0071200427
  },
  "dropped_23": {
    "CumulativeVarianceExplained": 0.6772274596,
    "Mask": "combined",
    "Method": "aCompCor",
    "Retained": false,
    "SingularValue": 43.1117900682,
    "VarianceExplained": 0.0066478046
  },
  "dropped_230": {
    "CumulativeVarianceExplained": 0.6138865772,
    "Mask": "WM",
    "Method": "aCompCor",
    "Retained": false,
    "SingularValue": 51.7521465569,
    "VarianceExplained": 0.0070803518
  },
  "dropped_231": {
    "CumulativeVarianceExplained": 0.6209111219,
    "Mask": "WM",
    "Method": "aCompCor",
    "Retained": false,
    "SingularValue": 51.5477890154,
    "VarianceExplained": 0.0070245448
  },
  "dropped_232": {
    "CumulativeVarianceExplained": 0.6278994478,
    "Mask": "WM",
    "Method": "aCompCor",
    "Retained": false,
    "SingularValue": 51.4147258323,
    "VarianceExplained": 0.0069883259
  },
  "dropped_233": {
    "CumulativeVarianceExplained": 0.6348244862,
    "Mask": "WM",
    "Method": "aCompCor",
    "Retained": false,
    "SingularValue": 51.1813858818,
    "VarianceExplained": 0.0069250384
  },
  "dropped_234": {
    "CumulativeVarianceExplained": 0.6416946951,
    "Mask": "WM",
    "Method": "aCompCor",
    "Retained": false,
    "SingularValue": 50.9783673223,
    "VarianceExplained": 0.0068702089
  },
  "dropped_235": {
    "CumulativeVarianceExplained": 0.6484863147,
    "Mask": "WM",
    "Method": "aCompCor",
    "Retained": false,
    "SingularValue": 50.6859540455,
    "VarianceExplained": 0.0067916196
  },
  "dropped_236": {
    "CumulativeVarianceExplained": 0.6552038547,
    "Mask": "WM",
    "Method": "aCompCor",
    "Retained": false,
    "SingularValue": 50.4087674899,
    "VarianceExplained": 0.00671754
  },
  "dropped_237": {
    "CumulativeVarianceExplained": 0.6618955155,
    "Mask": "WM",
    "Method": "aCompCor",
    "Retained": false,
    "SingularValue": 50.3115746782,
    "VarianceExplained": 0.0066916608
  },
  "dropped_238": {
    "CumulativeVarianceExplained": 0.6685168573,
    "Mask": "WM",
    "Method": "aCompCor",
    "Retained": false,
    "SingularValue": 50.0465279255,
    "VarianceExplained": 0.0066213418
  },
  "dropped_239": {
    "CumulativeVarianceExplained": 0.6750790618,
    "Mask": "WM",
    "Method": "aCompCor",
    "Retained": false,
    "SingularValue": 49.8225359859,
    "VarianceExplained": 0.0065622045
  },
  "dropped_24": {
    "CumulativeVarianceExplained": 0.6838488128,
    "Mask": "combined",
    "Method": "aCompCor",
    "Retained": false,
    "SingularValue": 43.0259345352,
    "VarianceExplained": 0.0066213532
  },
  "dropped_240": {
    "CumulativeVarianceExplained": 0.6815932564,
    "Mask": "WM",
    "Method": "aCompCor",
    "Retained": false,
    "SingularValue": 49.6399476575,
    "VarianceExplained": 0.0065141946
  },
  "dropped_241": {
    "CumulativeVarianceExplained": 0.6880802561,
    "Mask": "WM",
    "Method": "aCompCor",
    "Retained": false,
    "SingularValue": 49.5362227036,
    "VarianceExplained": 0.0064869997
  },
  "dropped_242": {
    "CumulativeVarianceExplained": 0.6945393433,
    "Mask": "WM",
    "Method": "aCompCor",
    "Retained": false,
    "SingularValue": 49.4295347761,
    "VarianceExplained": 0.0064590872
  },
  "dropped_243": {
    "CumulativeVarianceExplained": 0.7009400872,
    "Mask": "WM",
    "Method": "aCompCor",
    "Retained": false,
    "SingularValue": 49.2057864613,
    "VarianceExplained": 0.006400744
  },
  "dropped_244": {
    "CumulativeVarianceExplained": 0.7072995231,
    "Mask": "WM",
    "Method": "aCompCor",
    "Retained": false,
    "SingularValue": 49.0467514208,
    "VarianceExplained": 0.0063594359
  },
  "dropped_245": {
    "CumulativeVarianceExplained": 0.7136132309,
    "Mask": "WM",
    "Method": "aCompCor",
    "Retained": false,
    "SingularValue": 48.8700956248,
    "VarianceExplained": 0.0063137078
  },
  "dropped_246": {
    "CumulativeVarianceExplained": 0.7199085604,
    "Mask": "WM",
    "Method": "aCompCor",
    "Retained": false,
    "SingularValue": 48.798916793,
    "VarianceExplained": 0.0062953295
  },
  "dropped_247": {
    "CumulativeVarianceExplained": 0.7261431936,
    "Mask": "WM",
    "Method": "aCompCor",
    "Retained": false,
    "SingularValue": 48.5631000737,
    "VarianceExplained": 0.0062346332
  },
  "dropped_248": {
    "CumulativeVarianceExplained": 0.7323469228,
    "Mask": "WM",
    "Method": "aCompCor",
    "Retained": false,
    "SingularValue": 48.4425912258,
    "VarianceExplained": 0.0062037292
  },
  "dropped_249": {
    "CumulativeVarianceExplained": 0.738470023,
    "Mask": "WM",
    "Method": "aCompCor",
    "Retained": false,
    "SingularValue": 48.1267609757,
    "VarianceExplained": 0.0061231002
  },
  "dropped_25": {
    "CumulativeVarianceExplained": 0.6904520799,
    "Mask": "combined",
    "Method": "aCompCor",
    "Retained": false,
    "SingularValue": 42.9671319949,
    "VarianceExplained": 0.0066032671
  },
  "dropped_250": {
    "CumulativeVarianceExplained": 0.7445697786,
    "Mask": "WM",
    "Method": "aCompCor",
    "Retained": false,
    "SingularValue": 48.0349305205,
    "VarianceExplained": 0.0060997556
  },
  "dropped_251": {
    "CumulativeVarianceExplained": 0.7506333178,
    "Mask": "WM",
    "Method": "aCompCor",
    "Retained": false,
    "SingularValue": 47.8921181768,
    "VarianceExplained": 0.0060635392
  },
  "dropped_252": {
    "CumulativeVarianceExplained": 0.7566692855,
    "Mask": "WM",
    "Method": "aCompCor",
    "Retained": false,
    "SingularValue": 47.7831088469,
    "VarianceExplained": 0.0060359677
  },
  "dropped_253": {
    "CumulativeVarianceExplained": 0.7626231209,
    "Mask": "WM",
    "Method": "aCompCor",
    "Retained": false,
    "SingularValue": 47.4568996707,
    "VarianceExplained": 0.0059538354
  },
  "dropped_254": {
    "CumulativeVarianceExplained": 0.7685237199,
    "Mask": "WM",
    "Method": "aCompCor",
    "Retained": false,
    "SingularValue": 47.2442543246,
    "VarianceExplained": 0.005900599
  },
  "dropped_255": {
    "CumulativeVarianceExplained": 0.7744037309,
    "Mask": "WM",
    "Method": "aCompCor",
    "Retained": false,
    "SingularValue": 47.1617616027,
    "VarianceExplained": 0.005880011
  },
  "dropped_256": {
    "CumulativeVarianceExplained": 0.7802464119,
    "Mask": "WM",
    "Method": "aCompCor",
    "Retained": false,
    "SingularValue": 47.0118171613,
    "VarianceExplained": 0.005842681
  },
  "dropped_257": {
    "CumulativeVarianceExplained": 0.7860120347,
    "Mask": "WM",
    "Method": "aCompCor",
    "Retained": false,
    "SingularValue": 46.7007722308,
    "VarianceExplained": 0.0057656228
  },
  "dropped_258": {
    "CumulativeVarianceExplained": 0.7917700022,
    "Mask": "WM",
    "Method": "aCompCor",
    "Retained": false,
    "SingularValue": 46.6697589016,
    "VarianceExplained": 0.0057579676
  },
  "dropped_259": {
    "CumulativeVarianceExplained": 0.7974931237,
    "Mask": "WM",
    "Method": "aCompCor",
    "Retained": false,
    "SingularValue": 46.5283264764,
    "VarianceExplained": 0.0057231215
  },
  "dropped_26": {
    "CumulativeVarianceExplained": 0.6969574638,
    "Mask": "combined",
    "Method": "aCompCor",
    "Retained": false,
    "SingularValue": 42.6474823564,
    "VarianceExplained": 0.0065053839
  },
  "dropped_260": {
    "CumulativeVarianceExplained": 0.803194632,
    "Mask": "WM",
    "Method": "aCompCor",
    "Retained": false,
    "SingularValue": 46.4403868422,
    "VarianceExplained": 0.0057015083
  },
  "dropped_261": {
    "CumulativeVarianceExplained": 0.808827044,
    "Mask": "WM",
    "Method": "aCompCor",
    "Retained": false,
    "SingularValue": 46.1581247834,
    "VarianceExplained": 0.005632412
  },
  "dropped_262": {
    "CumulativeVarianceExplained": 0.8144160222,
    "Mask": "WM",
    "Method": "aCompCor",
    "Retained": false,
    "SingularValue": 45.9798086438,
    "VarianceExplained": 0.0055889783
  },
  "dropped_263": {
    "CumulativeVarianceExplained": 0.8199510287,
    "Mask": "WM",
    "Method": "aCompCor",
    "Retained": false,
    "SingularValue": 45.7572604155,
    "VarianceExplained": 0.0055350064
  },
  "dropped_264": {
    "CumulativeVarianceExplained": 0.8254242085,
    "Mask": "WM",
    "Method": "aCompCor",
    "Retained": false,
    "SingularValue": 45.5009860546,
    "VarianceExplained": 0.0054731798
  },
  "dropped_265": {
    "CumulativeVarianceExplained": 0.8308900597,
    "Mask": "WM",
    "Method": "aCompCor",
    "Retained": false,
    "SingularValue": 45.4705126768,
    "VarianceExplained": 0.0054658512
  },
  "dropped_266": {
    "CumulativeVarianceExplained": 0.8363029705,
    "Mask": "WM",
    "Method": "aCompCor",
    "Retained": false,
    "SingularValue": 45.2497709685,
    "VarianceExplained": 0.0054129108
  },
  "dropped_267": {
    "CumulativeVarianceExplained": 0.8417036304,
    "Mask": "WM",
    "Method": "aCompCor",
    "Retained": false,
    "SingularValue": 45.1985357534,
    "VarianceExplained": 0.0054006599
  },
  "dropped_268": {
    "CumulativeVarianceExplained": 0.8470488082,
    "Mask": "WM",
    "Method": "aCompCor",
    "Retained": false,
    "SingularValue": 44.9657694006,
    "VarianceExplained": 0.0053451778
  },
  "dropped_269": {
    "CumulativeVarianceExplained": 0.8523804579,
    "Mask": "WM",
    "Method": "aCompCor",
    "Retained": false,
    "SingularValue": 44.9088312446,
    "VarianceExplained": 0.0053316497
  },
  "dropped_27": {
    "CumulativeVarianceExplained": 0.7034480438,
    "Mask": "combined",
    "Method": "aCompCor",
    "Retained": false,
    "SingularValue": 42.5989298751,
    "VarianceExplained": 0.0064905801
  },
  "dropped_270": {
    "CumulativeVarianceExplained": 0.8576812042,
    "Mask": "WM",
    "Method": "aCompCor",
    "Retained": false,
    "SingularValue": 44.778491561,
    "VarianceExplained": 0.0053007463
  },
  "dropped_271": {
    "CumulativeVarianceExplained": 0.862943451,
    "Mask": "WM",
    "Method": "aCompCor",
    "Retained": false,
    "SingularValue": 44.6155813203,
    "VarianceExplained": 0.0052622468
  },
  "dropped_272": {
    "CumulativeVarianceExplained": 0.8681472997,
    "Mask": "WM",
    "Method": "aCompCor",
    "Retained": false,
    "SingularValue": 44.3673286804,
    "VarianceExplained": 0.0052038487
  },
  "dropped_273": {
    "CumulativeVarianceExplained": 0.8733418911,
    "Mask": "WM",
    "Method": "aCompCor",
    "Retained": false,
    "SingularValue": 44.3278474913,
    "VarianceExplained": 0.0051945913
  },
  "dropped_274": {
    "CumulativeVarianceExplained": 0.8784648169,
    "Mask": "WM",
    "Method": "aCompCor",
    "Retained": false,
    "SingularValue": 44.021007876,
    "VarianceExplained": 0.0051229258
  },
  "dropped_275": {
    "CumulativeVarianceExplained": 0.883572658,
    "Mask": "WM",
    "Method": "aCompCor",
    "Retained": false,
    "SingularValue": 43.9561492184,
    "VarianceExplained": 0.0051078411
  },
  "dropped_276": {
    "CumulativeVarianceExplained": 0.8886406956,
    "Mask": "WM",
    "Method": "aCompCor",
    "Retained": false,
    "SingularValue": 43.7845474798,
    "VarianceExplained": 0.0050680376
  },
  "dropped_277": {
    "CumulativeVarianceExplained": 0.8936542463,
    "Mask": "WM",
    "Method": "aCompCor",
    "Retained": false,
    "SingularValue": 43.548545452,
    "VarianceExplained": 0.0050135507
  },
  "dropped_278": {
    "CumulativeVarianceExplained": 0.8986125129,
    "Mask": "WM",
    "Method": "aCompCor",
    "Retained": false,
    "SingularValue": 43.3077766023,
    "VarianceExplained": 0.0049582666
  },
  "dropped_279": {
    "CumulativeVarianceExplained": 0.9035048291,
    "Mask": "WM",
    "Method": "aCompCor",
    "Retained": false,
    "SingularValue": 43.0187919859,
    "VarianceExplained": 0.0048923162
  },
  "dropped_28": {
    "CumulativeVarianceExplained": 0.7098678511,
    "Mask": "combined",
    "Method": "aCompCor",
    "Retained": false,
    "SingularValue": 42.3660456076,
    "VarianceExplained": 0.0064198073
  },
  "dropped_280": {
    "CumulativeVarianceExplained": 0.9083532646,
    "Mask": "WM",
    "Method": "aCompCor",
    "Retained": false,
    "SingularValue": 42.8254328619,
    "VarianceExplained": 0.0048484355
  },
  "dropped_281": {
    "CumulativeVarianceExplained": 0.9131919984,
    "Mask": "WM",
    "Method": "aCompCor",
    "Retained": false,
    "SingularValue": 42.7825643842,
    "VarianceExplained": 0.0048387337
  },
  "dropped_282": {
    "CumulativeVarianceExplained": 0.9179950225,
    "Mask": "WM",
    "Method": "aCompCor",
    "Retained": false,
    "SingularValue": 42.6244055408,
    "VarianceExplained": 0.0048030242
  },
  "dropped_283": {
    "CumulativeVarianceExplained": 0.9227373925,
    "Mask": "WM",
    "Method": "aCompCor",
    "Retained": false,
    "SingularValue": 42.3544128377,
    "VarianceExplained": 0.00474237
  },
  "dropped_284": {
    "CumulativeVarianceExplained": 0.9274457643,
    "Mask": "WM",
    "Method": "aCompCor",
    "Retained": false,
    "SingularValue": 42.2023199283,
    "VarianceExplained": 0.0047083718
  },
  "dropped_285": {
    "CumulativeVarianceExplained": 0.9321122272,
    "Mask": "WM",
    "Method": "aCompCor",
    "Retained": false,
    "SingularValue": 42.0140797334,
    "VarianceExplained": 0.0046664628
  },
  "dropped_286": {
    "CumulativeVarianceExplained": 0.9367427675,
    "Mask": "WM",
    "Method": "aCompCor",
    "Retained": false,
    "SingularValue": 41.8520549193,
    "VarianceExplained": 0.0046305404
  },
  "dropped_287": {
    "CumulativeVarianceExplained": 0.9413331093,
    "Mask": "WM",
    "Method": "aCompCor",
    "Retained": false,
    "SingularValue": 41.6699962034,
    "VarianceExplained": 0.0045903418
  },
  "dropped_288": {
    "CumulativeVarianceExplained": 0.9458944077,
    "Mask": "WM",
    "Method": "aCompCor",
    "Retained": false,
    "SingularValue": 41.5379625727,
    "VarianceExplained": 0.0045612984
  },
  "dropped_289": {
    "CumulativeVarianceExplained": 0.9504295391,
    "Mask": "WM",
    "Method": "aCompCor",
    "Retained": false,
    "SingularValue": 41.4186449979,
    "VarianceExplained": 0.0045351314
  },
  "dropped_29": {
    "CumulativeVarianceExplained": 0.7162766465,
    "Mask": "combined",
    "Method": "aCompCor",
    "Retained": false,
    "SingularValue": 42.3296948237,
    "VarianceExplained": 0.0064087954
  },
  "dropped_290": {
    "CumulativeVarianceExplained": 0.954855747,
    "Mask": "WM",
    "Method": "aCompCor",
    "Retained": false,
    "SingularValue": 40.9182315289,
    "VarianceExplained": 0.0044262079
  },
  "dropped_291": {
    "CumulativeVarianceExplained": 0.9592226724,
    "Mask": "WM",
    "Method": "aCompCor",
    "Retained": false,
    "SingularValue": 40.6432882121,
    "VarianceExplained": 0.0043669254
  },
  "dropped_292": {
    "CumulativeVarianceExplained": 0.9635377035,
    "Mask": "WM",
    "Method": "aCompCor",
    "Retained": false,
    "SingularValue": 40.4010743311,
    "VarianceExplained": 0.0043150311
  },
  "dropped_293": {
    "CumulativeVarianceExplained": 0.9677964059,
    "Mask": "WM",
    "Method": "aCompCor",
    "Retained": false,
    "SingularValue": 40.136508997,
    "VarianceExplained": 0.0042587024
  },
  "dropped_294": {
    "CumulativeVarianceExplained": 0.972025902,
    "Mask": "WM",
    "Method": "aCompCor",
    "Retained": false,
    "SingularValue": 39.9986437331,
    "VarianceExplained": 0.0042294961
  },
  "dropped_295": {
    "CumulativeVarianceExplained": 0.976184758,
    "Mask": "WM",
    "Method": "aCompCor",
    "Retained": false,
    "SingularValue": 39.6632130953,
    "VarianceExplained": 0.004158856
  },
  "dropped_296": {
    "CumulativeVarianceExplained": 0.9803049179,
    "Mask": "WM",
    "Method": "aCompCor",
    "Retained": false,
    "SingularValue": 39.4782583481,
    "VarianceExplained": 0.0041201599
  },
  "dropped_297": {
    "CumulativeVarianceExplained": 0.9843334435,
    "Mask": "WM",
    "Method": "aCompCor",
    "Retained": false,
    "SingularValue": 39.0367822437,
    "VarianceExplained": 0.0040285256
  },
  "dropped_298": {
    "CumulativeVarianceExplained": 0.9883332046,
    "Mask": "WM",
    "Method": "aCompCor",
    "Retained": false,
    "SingularValue": 38.8971676126,
    "VarianceExplained": 0.0039997611
  },
  "dropped_299": {
    "CumulativeVarianceExplained": 0.9922602504,
    "Mask": "WM",
    "Method": "aCompCor",
    "Retained": false,
    "SingularValue": 38.5419717944,
    "VarianceExplained": 0.0039270457
  },
  "dropped_3": {
    "CumulativeVarianceExplained": 0.5330090785,
    "Mask": "combined",
    "Method": "aCompCor",
    "Retained": false,
    "SingularValue": 46.8680447732,
    "VarianceExplained": 0.0078566934
  },
  "dropped_30": {
    "CumulativeVarianceExplained": 0.722591158,
    "Mask": "combined",
    "Method": "aCompCor",
    "Retained": false,
    "SingularValue": 42.0171714711,
    "VarianceExplained": 0.0063145115
  },
  "dropped_300": {
    "CumulativeVarianceExplained": 0.9961778921,
    "Mask": "WM",
    "Method": "aCompCor",
    "Retained": false,
    "SingularValue": 38.4957961776,
    "VarianceExplained": 0.0039176417
  },
  "dropped_301": {
    "CumulativeVarianceExplained": 1.0,
    "Mask": "WM",
    "Method": "aCompCor",
    "Retained": false,
    "SingularValue": 38.0235291249,
    "VarianceExplained": 0.0038221079
  },
  "dropped_302": {
    "CumulativeVarianceExplained": 1.0,
    "Mask": "WM",
    "Method": "aCompCor",
    "Retained": false,
    "SingularValue": 0.0,
    "VarianceExplained": 0.0
  },
  "dropped_303": {
    "CumulativeVarianceExplained": 1.0,
    "Mask": "WM",
    "Method": "aCompCor",
    "Retained": false,
    "SingularValue": 0.0,
    "VarianceExplained": 0.0
  },
  "dropped_304": {
    "CumulativeVarianceExplained": 1.0,
    "Mask": "WM",
    "Method": "aCompCor",
    "Retained": false,
    "SingularValue": 0.0,
    "VarianceExplained": 0.0
  },
  "dropped_305": {
    "CumulativeVarianceExplained": 1.0,
    "Mask": "WM",
    "Method": "aCompCor",
    "Retained": false,
    "SingularValue": 0.0,
    "VarianceExplained": 0.0
  },
  "dropped_31": {
    "CumulativeVarianceExplained": 0.7288852786,
    "Mask": "combined",
    "Method": "aCompCor",
    "Retained": false,
    "SingularValue": 41.949275339,
    "VarianceExplained": 0.0062941206
  },
  "dropped_32": {
    "CumulativeVarianceExplained": 0.7351012282,
    "Mask": "combined",
    "Method": "aCompCor",
    "Retained": false,
    "SingularValue": 41.6879631955,
    "VarianceExplained": 0.0062159496
  },
  "dropped_33": {
    "CumulativeVarianceExplained": 0.7412087023,
    "Mask": "combined",
    "Method": "aCompCor",
    "Retained": false,
    "SingularValue": 41.3226105208,
    "VarianceExplained": 0.0061074741
  },
  "dropped_34": {
    "CumulativeVarianceExplained": 0.747254467,
    "Mask": "combined",
    "Method": "aCompCor",
    "Retained": false,
    "SingularValue": 41.1133203087,
    "VarianceExplained": 0.0060457646
  },
  "dropped_35": {
    "CumulativeVarianceExplained": 0.7532719766,
    "Mask": "combined",
    "Method": "aCompCor",
    "Retained": false,
    "SingularValue": 41.0171358532,
    "VarianceExplained": 0.0060175096
  },
  "dropped_36": {
    "CumulativeVarianceExplained": 0.7592634513,
    "Mask": "combined",
    "Method": "aCompCor",
    "Retained": false,
    "SingularValue": 40.9283087126,
    "VarianceExplained": 0.0059914747
  },
  "dropped_37": {
    "CumulativeVarianceExplained": 0.765208953,
    "Mask": "combined",
    "Method": "aCompCor",
    "Retained": false,
    "SingularValue": 40.7709834147,
    "VarianceExplained": 0.0059455017
  },
  "dropped_38": {
    "CumulativeVarianceExplained": 0.7711253089,
    "Mask": "combined",
    "Method": "aCompCor",
    "Retained": false,
    "SingularValue": 40.6709278281,
    "VarianceExplained": 0.0059163559
  },
  "dropped_39": {
    "CumulativeVarianceExplained": 0.7770101403,
    "Mask": "combined",
    "Method": "aCompCor",
    "Retained": false,
    "SingularValue": 40.5624283069,
    "VarianceExplained": 0.0058848314
  },
  "dropped_4": {
    "CumulativeVarianceExplained": 0.5407645964,
    "Mask": "combined",
    "Method": "aCompCor",
    "Retained": false,
    "SingularValue": 46.5652926339,
    "VarianceExplained": 0.0077555179
  },
  "dropped_40": {
    "CumulativeVarianceExplained": 0.7828522963,
    "Mask": "combined",
    "Method": "aCompCor",
    "Retained": false,
    "SingularValue": 40.4150859335,
    "VarianceExplained": 0.0058421559
  },
  "dropped_41": {
    "CumulativeVarianceExplained": 0.7886114532,
    "Mask": "combined",
    "Method": "aCompCor",
    "Retained": false,
    "SingularValue": 40.1269722025,
    "VarianceExplained": 0.005759157
  },
  "dropped_42": {
    "CumulativeVarianceExplained": 0.7943260078,
    "Mask": "combined",
    "Method": "aCompCor",
    "Retained": false,
    "SingularValue": 39.971286364,
    "VarianceExplained": 0.0057145545
  },
  "dropped_43": {
    "CumulativeVarianceExplained": 0.8000074775,
    "Mask": "combined",
    "Method": "aCompCor",
    "Retained": false,
    "SingularValue": 39.8554099761,
    "VarianceExplained": 0.0056814697
  },
  "dropped_44": {
    "CumulativeVarianceExplained": 0.805645541,
    "Mask": "combined",
    "Method": "aCompCor",
    "Retained": false,
    "SingularValue": 39.7028715068,
    "VarianceExplained": 0.0056380636
  },
  "dropped_45": {
    "CumulativeVarianceExplained": 0.811243384,
    "Mask": "combined",
    "Method": "aCompCor",
    "Retained": false,
    "SingularValue": 39.5610025462,
    "VarianceExplained": 0.005597843
  },
  "dropped_46": {
    "CumulativeVarianceExplained": 0.8167652925,
    "Mask": "combined",
    "Method": "aCompCor",
    "Retained": false,
    "SingularValue": 39.2917648027,
    "VarianceExplained": 0.0055219085
  },
  "dropped_47": {
    "CumulativeVarianceExplained": 0.8222487674,
    "Mask": "combined",
    "Method": "aCompCor",
    "Retained": false,
    "SingularValue": 39.1547868148,
    "VarianceExplained": 0.0054834749
  },
  "dropped_48": {
    "CumulativeVarianceExplained": 0.8277157014,
    "Mask": "combined",
    "Method": "aCompCor",
    "Retained": false,
    "SingularValue": 39.0956869511,
    "VarianceExplained": 0.005466934
  },
  "dropped_49": {
    "CumulativeVarianceExplained": 0.8330846857,
    "Mask": "combined",
    "Method": "aCompCor",
    "Retained": false,
    "SingularValue": 38.7438702349,
    "VarianceExplained": 0.0053689843
  },
  "dropped_5": {
    "CumulativeVarianceExplained": 0.5484573008,
    "Mask": "combined",
    "Method": "aCompCor",
    "Retained": false,
    "SingularValue": 46.3763383414,
    "VarianceExplained": 0.0076927044
  },
  "dropped_50": {
    "CumulativeVarianceExplained": 0.8384466447,
    "Mask": "combined",
    "Method": "aCompCor",
    "Retained": false,
    "SingularValue": 38.7185138481,
    "VarianceExplained": 0.005361959
  },
  "dropped_51": {
    "CumulativeVarianceExplained": 0.8437890407,
    "Mask": "combined",
    "Method": "aCompCor",
    "Retained": false,
    "SingularValue": 38.6478173741,
    "VarianceExplained": 0.005342396
  },
  "dropped_52": {
    "CumulativeVarianceExplained": 0.8490560492,
    "Mask": "combined",
    "Method": "aCompCor",
    "Retained": false,
    "SingularValue": 38.374165443,
    "VarianceExplained": 0.0052670085
  },
  "dropped_53": {
    "CumulativeVarianceExplained": 0.8542775157,
    "Mask": "combined",
    "Method": "aCompCor",
    "Retained": false,
    "SingularValue": 38.207901208,
    "VarianceExplained": 0.0052214665
  },
  "dropped_54": {
    "CumulativeVarianceExplained": 0.8594686666,
    "Mask": "combined",
    "Method": "aCompCor",
    "Retained": false,
    "SingularValue": 38.0968229253,
    "VarianceExplained": 0.0051911509
  },
  "dropped_55": {
    "CumulativeVarianceExplained": 0.8646389813,
    "Mask": "combined",
    "Method": "aCompCor",
    "Retained": false,
    "SingularValue": 38.0202898728,
    "VarianceExplained": 0.0051703147
  },
  "dropped_56": {
    "CumulativeVarianceExplained": 0.8697046008,
    "Mask": "combined",
    "Method": "aCompCor",
    "Retained": false,
    "SingularValue": 37.6333792004,
    "VarianceExplained": 0.0050656195
  },
  "dropped_57": {
    "CumulativeVarianceExplained": 0.8746971576,
    "Mask": "combined",
    "Method": "aCompCor",
    "Retained": false,
    "SingularValue": 37.3609954279,
    "VarianceExplained": 0.0049925568
  },
  "dropped_58": {
    "CumulativeVarianceExplained": 0.8796783317,
    "Mask": "combined",
    "Method": "aCompCor",
    "Retained": false,
    "SingularValue": 37.3183811681,
    "VarianceExplained": 0.0049811741
  },
  "dropped_59": {
    "CumulativeVarianceExplained": 0.8846205438,
    "Mask": "combined",
    "Method": "aCompCor",
    "Retained": false,
    "SingularValue": 37.1721449946,
    "VarianceExplained": 0.0049422121
  },
  "dropped_6": {
    "CumulativeVarianceExplained": 0.5561022562,
    "Mask": "combined",
    "Method": "aCompCor",
    "Retained": false,
    "SingularValue": 46.2321842072,
    "VarianceExplained": 0.0076449554
  },
  "dropped_60": {
    "CumulativeVarianceExplained": 0.8895267381,
    "Mask": "combined",
    "Method": "aCompCor",
    "Retained": false,
    "SingularValue": 37.036446158,
    "VarianceExplained": 0.0049061943
  },
  "dropped_61": {
    "CumulativeVarianceExplained": 0.8943807235,
    "Mask": "combined",
    "Method": "aCompCor",
    "Retained": false,
    "SingularValue": 36.8388583012,
    "VarianceExplained": 0.0048539853
  },
  "dropped_62": {
    "CumulativeVarianceExplained": 0.8992221001,
    "Mask": "combined",
    "Method": "aCompCor",
    "Retained": false,
    "SingularValue": 36.7909810859,
    "VarianceExplained": 0.0048413766
  },
  "dropped_63": {
    "CumulativeVarianceExplained": 0.903979159,
    "Mask": "combined",
    "Method": "aCompCor",
    "Retained": false,
    "SingularValue": 36.4691967975,
    "VarianceExplained": 0.0047570589
  },
  "dropped_64": {
    "CumulativeVarianceExplained": 0.9087092229,
    "Mask": "combined",
    "Method": "aCompCor",
    "Retained": false,
    "SingularValue": 36.3655731687,
    "VarianceExplained": 0.0047300639
  },
  "dropped_65": {
    "CumulativeVarianceExplained": 0.9134143648,
    "Mask": "combined",
    "Method": "aCompCor",
    "Retained": false,
    "SingularValue": 36.2696442215,
    "VarianceExplained": 0.0047051419
  },
  "dropped_66": {
    "CumulativeVarianceExplained": 0.9180859545,
    "Mask": "combined",
    "Method": "aCompCor",
    "Retained": false,
    "SingularValue": 36.140094118,
    "VarianceExplained": 0.0046715897
  },
  "dropped_67": {
    "CumulativeVarianceExplained": 0.9227140219,
    "Mask": "combined",
    "Method": "aCompCor",
    "Retained": false,
    "SingularValue": 35.9713529567,
    "VarianceExplained": 0.0046280674
  },
  "dropped_68": {
    "CumulativeVarianceExplained": 0.9272892961,
    "Mask": "combined",
    "Method": "aCompCor",
    "Retained": false,
    "SingularValue": 35.7655986283,
    "VarianceExplained": 0.0045752742
  },
  "dropped_69": {
    "CumulativeVarianceExplained": 0.9317987176,
    "Mask": "combined",
    "Method": "aCompCor",
    "Retained": false,
    "SingularValue": 35.5072754331,
    "VarianceExplained": 0.0045094215
  },
  "dropped_7": {
    "CumulativeVarianceExplained": 0.5637210847,
    "Mask": "combined",
    "Method": "aCompCor",
    "Retained": false,
    "SingularValue": 46.1531167254,
    "VarianceExplained": 0.0076188286
  },
  "dropped_70": {
    "CumulativeVarianceExplained": 0.9362944205,
    "Mask": "combined",
    "Method": "aCompCor",
    "Retained": false,
    "SingularValue": 35.4532238273,
    "VarianceExplained": 0.0044957028
  },
  "dropped_71": {
    "CumulativeVarianceExplained": 0.940705548,
    "Mask": "combined",
    "Method": "aCompCor",
    "Retained": false,
    "SingularValue": 35.1181589364,
    "VarianceExplained": 0.0044111275
  },
  "dropped_72": {
    "CumulativeVarianceExplained": 0.9450907769,
    "Mask": "combined",
    "Method": "aCompCor",
    "Retained": false,
    "SingularValue": 35.0149141954,
    "VarianceExplained": 0.0043852289
  },
  "dropped_73": {
    "CumulativeVarianceExplained": 0.9494665675,
    "Mask": "combined",
    "Method": "aCompCor",
    "Retained": false,
    "SingularValue": 34.9772129601,
    "VarianceExplained": 0.0043757906
  },
  "dropped_74": {
    "CumulativeVarianceExplained": 0.9537423537,
    "Mask": "combined",
    "Method": "aCompCor",
    "Retained": false,
    "SingularValue": 34.5752178248,
    "VarianceExplained": 0.0042757862
  },
  "dropped_75": {
    "CumulativeVarianceExplained": 0.9580050703,
    "Mask": "combined",
    "Method": "aCompCor",
    "Retained": false,
    "SingularValue": 34.5223351324,
    "VarianceExplained": 0.0042627166
  },
  "dropped_76": {
    "CumulativeVarianceExplained": 0.9621453856,
    "Mask": "combined",
    "Method": "aCompCor",
    "Retained": false,
    "SingularValue": 34.0230813063,
    "VarianceExplained": 0.0041403153
  },
  "dropped_77": {
    "CumulativeVarianceExplained": 0.9662108794,
    "Mask": "combined",
    "Method": "aCompCor",
    "Retained": false,
    "SingularValue": 33.714256093,
    "VarianceExplained": 0.0040654937
  },
  "dropped_78": {
    "CumulativeVarianceExplained": 0.9702503805,
    "Mask": "combined",
    "Method": "aCompCor",
    "Retained": false,
    "SingularValue": 33.6063076184,
    "VarianceExplained": 0.0040395011
  },
  "dropped_79": {
    "CumulativeVarianceExplained": 0.9742279573,
    "Mask": "combined",
    "Method": "aCompCor",
    "Retained": false,
    "SingularValue": 33.3477260107,
    "VarianceExplained": 0.0039775769
  },
  "dropped_8": {
    "CumulativeVarianceExplained": 0.5712437276,
    "Mask": "combined",
    "Method": "aCompCor",
    "Retained": false,
    "SingularValue": 45.8608558408,
    "VarianceExplained": 0.0075226428
  },
  "dropped_80": {
    "CumulativeVarianceExplained": 0.9781213613,
    "Mask": "combined",
    "Method": "aCompCor",
    "Retained": false,
    "SingularValue": 32.9929893101,
    "VarianceExplained": 0.003893404
  },
  "dropped_81": {
    "CumulativeVarianceExplained": 0.9819684466,
    "Mask": "combined",
    "Method": "aCompCor",
    "Retained": false,
    "SingularValue": 32.7961485107,
    "VarianceExplained": 0.0038470853
  },
  "dropped_82": {
    "CumulativeVarianceExplained": 0.985746535,
    "Mask": "combined",
    "Method": "aCompCor",
    "Retained": false,
    "SingularValue": 32.5007205938,
    "VarianceExplained": 0.0037780884
  },
  "dropped_83": {
    "CumulativeVarianceExplained": 0.989471579,
    "Mask": "combined",
    "Method": "aCompCor",
    "Retained": false,
    "SingularValue": 32.2717587338,
    "VarianceExplained": 0.0037250439
  },
  "dropped_84": {
    "CumulativeVarianceExplained": 0.9930497807,
    "Mask": "combined",
    "Method": "aCompCor",
    "Retained": false,
    "SingularValue": 31.6292830654,
    "VarianceExplained": 0.0035782018
  },
  "dropped_85": {
    "CumulativeVarianceExplained": 0.9965929634,
    "Mask": "combined",
    "Method": "aCompCor",
    "Retained": false,
    "SingularValue": 31.4741275988,
    "VarianceExplained": 0.0035431826
  },
  "dropped_86": {
    "CumulativeVarianceExplained": 1.0,
    "Mask": "combined",
    "Method": "aCompCor",
    "Retained": false,
    "SingularValue": 30.8635114815,
    "VarianceExplained": 0.0034070366
  },
  "dropped_87": {
    "CumulativeVarianceExplained": 1.0,
    "Mask": "combined",
    "Method": "aCompCor",
    "Retained": false,
    "SingularValue": 0.0,
    "VarianceExplained": 0.0
  },
  "dropped_88": {
    "CumulativeVarianceExplained": 1.0,
    "Mask": "combined",
    "Method": "aCompCor",
    "Retained": false,
    "SingularValue": 0.0,
    "VarianceExplained": 0.0
  },
  "dropped_89": {
    "CumulativeVarianceExplained": 1.0,
    "Mask": "combined",
    "Method": "aCompCor",
    "Retained": false,
    "SingularValue": 0.0,
    "VarianceExplained": 0.0
  },
  "dropped_9": {
    "CumulativeVarianceExplained": 0.5787153412,
    "Mask": "combined",
    "Method": "aCompCor",
    "Retained": false,
    "SingularValue": 45.7050444144,
    "VarianceExplained": 0.0074716136
  },
  "dropped_90": {
    "CumulativeVarianceExplained": 1.0,
    "Mask": "combined",
    "Method": "aCompCor",
    "Retained": false,
    "SingularValue": 0.0,
    "VarianceExplained": 0.0
  },
  "dropped_91": {
    "CumulativeVarianceExplained": 0.5377706611,
    "Mask": "CSF",
    "Method": "aCompCor",
    "Retained": false,
    "SingularValue": 35.6560974819,
    "VarianceExplained": 0.0199946102
  },
  "dropped_92": {
    "CumulativeVarianceExplained": 0.5559794577,
    "Mask": "CSF",
    "Method": "aCompCor",
    "Retained": false,
    "SingularValue": 34.0265532731,
    "VarianceExplained": 0.0182087965
  },
  "dropped_93": {
    "CumulativeVarianceExplained": 0.5733539727,
    "Mask": "CSF",
    "Method": "aCompCor",
    "Retained": false,
    "SingularValue": 33.2379081895,
    "VarianceExplained": 0.0173745151
  },
  "dropped_94": {
    "CumulativeVarianceExplained": 0.5895022228,
    "Mask": "CSF",
    "Method": "aCompCor",
    "Retained": false,
    "SingularValue": 32.043509215,
    "VarianceExplained": 0.0161482501
  },
  "dropped_95": {
    "CumulativeVarianceExplained": 0.6042854046,
    "Mask": "CSF",
    "Method": "aCompCor",
    "Retained": false,
    "SingularValue": 30.6592337437,
    "VarianceExplained": 0.0147831818
  },
  "dropped_96": {
    "CumulativeVarianceExplained": 0.6180653355,
    "Mask": "CSF",
    "Method": "aCompCor",
    "Retained": false,
    "SingularValue": 29.6006234018,
    "VarianceExplained": 0.0137799309
  },
  "dropped_97": {
    "CumulativeVarianceExplained": 0.6306243072,
    "Mask": "CSF",
    "Method": "aCompCor",
    "Retained": false,
    "SingularValue": 28.2588430901,
    "VarianceExplained": 0.0125589717
  },
  "dropped_98": {
    "CumulativeVarianceExplained": 0.6417738353,
    "Mask": "CSF",
    "Method": "aCompCor",
    "Retained": false,
    "SingularValue": 26.6259787215,
    "VarianceExplained": 0.0111495281
  },
  "dropped_99": {
    "CumulativeVarianceExplained": 0.6528140057,
    "Mask": "CSF",
    "Method": "aCompCor",
    "Retained": false,
    "SingularValue": 26.495079526,
    "VarianceExplained": 0.0110401705
  },
  "t_comp_cor_00": {
    "CumulativeVarianceExplained": 0.1802437154,
    "Method": "tCompCor",
    "Retained": true,
    "SingularValue": 94.6282610015,
    "VarianceExplained": 0.1802437154
  },
  "t_comp_cor_01": {
    "CumulativeVarianceExplained": 0.2939542621,
    "Method": "tCompCor",
    "Retained": true,
    "SingularValue": 75.1607607713,
    "VarianceExplained": 0.1137105467
  },
  "t_comp_cor_02": {
    "CumulativeVarianceExplained": 0.3972423637,
    "Method": "tCompCor",
    "Retained": true,
    "SingularValue": 71.6334620642,
    "VarianceExplained": 0.1032881016
  },
  "t_comp_cor_03": {
    "CumulativeVarianceExplained": 0.4655101623,
    "Method": "tCompCor",
    "Retained": true,
    "SingularValue": 58.2369662377,
    "VarianceExplained": 0.0682677986
  },
  "t_comp_cor_04": {
    "CumulativeVarianceExplained": 0.5175665643,
    "Method": "tCompCor",
    "Retained": true,
    "SingularValue": 50.8543218333,
    "VarianceExplained": 0.052056402
  }
}